package com.google.android.apps.plus.service;

import android.app.IntentService;

public class EsSyncAdapterService$MandatorySyncService
  extends IntentService
{
  public EsSyncAdapterService$MandatorySyncService()
  {
    super("MandatorySyncService");
    setIntentRedelivery(false);
  }
  
  /* Error */
  protected void onHandleIntent(android.content.Intent paramIntent)
  {
    // Byte code:
    //   0: aload_0
    //   1: ldc 25
    //   3: invokestatic 31	mbb:a	(Landroid/content/Context;Ljava/lang/Class;)Ljava/lang/Object;
    //   6: checkcast 25	gjm
    //   9: astore 8
    //   11: aload_0
    //   12: ldc 33
    //   14: invokestatic 31	mbb:a	(Landroid/content/Context;Ljava/lang/Class;)Ljava/lang/Object;
    //   17: checkcast 33	giz
    //   20: astore 9
    //   22: aload_0
    //   23: ldc 35
    //   25: invokestatic 31	mbb:a	(Landroid/content/Context;Ljava/lang/Class;)Ljava/lang/Object;
    //   28: checkcast 35	ilb
    //   31: astore 10
    //   33: aload 10
    //   35: getstatic 40	com/google/android/apps/plus/service/EsSyncAdapterService:a	Lild;
    //   38: invokeinterface 43 2 0
    //   43: aload 8
    //   45: invokeinterface 46 1 0
    //   50: astore 18
    //   52: aload 18
    //   54: arraylength
    //   55: istore 19
    //   57: iconst_0
    //   58: istore 20
    //   60: iload 20
    //   62: iload 19
    //   64: if_icmpge +68 -> 132
    //   67: aload 18
    //   69: iload 20
    //   71: aaload
    //   72: getfield 51	gjj:a	Ljava/lang/String;
    //   75: astore 21
    //   77: aload 9
    //   79: aload 21
    //   81: invokeinterface 54 2 0
    //   86: istore 24
    //   88: aload 9
    //   90: iload 24
    //   92: invokeinterface 58 2 0
    //   97: istore 25
    //   99: iload 25
    //   101: ifne +59 -> 160
    //   104: iinc 20 1
    //   107: goto -47 -> 60
    //   110: astore 11
    //   112: ldc 60
    //   114: bipush 6
    //   116: invokestatic 66	android/util/Log:isLoggable	(Ljava/lang/String;I)Z
    //   119: ifeq +13 -> 132
    //   122: ldc 60
    //   124: ldc 68
    //   126: aload 11
    //   128: invokestatic 72	android/util/Log:e	(Ljava/lang/String;Ljava/lang/String;Ljava/lang/Throwable;)I
    //   131: pop
    //   132: getstatic 75	com/google/android/apps/plus/service/EsSyncAdapterService:c	Ljava/lang/Object;
    //   135: astore 12
    //   137: aload 12
    //   139: monitorenter
    //   140: getstatic 79	com/google/android/apps/plus/service/EsSyncAdapterService:d	Landroid/os/PowerManager$WakeLock;
    //   143: astore 14
    //   145: aload 14
    //   147: ifnull +9 -> 156
    //   150: getstatic 79	com/google/android/apps/plus/service/EsSyncAdapterService:d	Landroid/os/PowerManager$WakeLock;
    //   153: invokevirtual 84	android/os/PowerManager$WakeLock:release	()V
    //   156: aload 12
    //   158: monitorexit
    //   159: return
    //   160: aload 9
    //   162: iload 24
    //   164: invokeinterface 87 2 0
    //   169: astore 26
    //   171: aload 26
    //   173: ldc 89
    //   175: invokeinterface 94 2 0
    //   180: ifne -76 -> 104
    //   183: aload 26
    //   185: ldc 96
    //   187: invokeinterface 94 2 0
    //   192: ifne +15 -> 207
    //   195: aload 26
    //   197: ldc 98
    //   199: invokeinterface 94 2 0
    //   204: ifeq -100 -> 104
    //   207: aload 26
    //   209: ldc 100
    //   211: invokeinterface 94 2 0
    //   216: ifne -112 -> 104
    //   219: new 102	android/accounts/Account
    //   222: dup
    //   223: aload 21
    //   225: ldc 104
    //   227: invokespecial 107	android/accounts/Account:<init>	(Ljava/lang/String;Ljava/lang/String;)V
    //   230: astore 27
    //   232: aload 27
    //   234: aload_0
    //   235: invokestatic 112	com/google/android/apps/plus/content/EsProvider:a	(Landroid/content/Context;)Ljava/lang/String;
    //   238: iconst_1
    //   239: invokestatic 118	android/content/ContentResolver:setIsSyncable	(Landroid/accounts/Account;Ljava/lang/String;I)V
    //   242: new 120	android/os/Bundle
    //   245: dup
    //   246: invokespecial 122	android/os/Bundle:<init>	()V
    //   249: astore 28
    //   251: aload 28
    //   253: ldc 124
    //   255: iconst_1
    //   256: invokevirtual 128	android/os/Bundle:putBoolean	(Ljava/lang/String;Z)V
    //   259: aload 28
    //   261: ldc 130
    //   263: iconst_1
    //   264: invokevirtual 128	android/os/Bundle:putBoolean	(Ljava/lang/String;Z)V
    //   267: aload 27
    //   269: aload_0
    //   270: invokestatic 112	com/google/android/apps/plus/content/EsProvider:a	(Landroid/content/Context;)Ljava/lang/String;
    //   273: aload 28
    //   275: invokestatic 134	android/content/ContentResolver:requestSync	(Landroid/accounts/Account;Ljava/lang/String;Landroid/os/Bundle;)V
    //   278: aload_0
    //   279: aload 27
    //   281: invokestatic 138	com/google/android/apps/plus/service/EsSyncAdapterService:b	(Landroid/content/Context;Landroid/accounts/Account;)V
    //   284: goto -180 -> 104
    //   287: astore 22
    //   289: ldc 60
    //   291: ldc 140
    //   293: aload 22
    //   295: invokestatic 72	android/util/Log:e	(Ljava/lang/String;Ljava/lang/String;Ljava/lang/Throwable;)I
    //   298: pop
    //   299: goto -195 -> 104
    //   302: astore_2
    //   303: getstatic 75	com/google/android/apps/plus/service/EsSyncAdapterService:c	Ljava/lang/Object;
    //   306: astore_3
    //   307: aload_3
    //   308: monitorenter
    //   309: getstatic 79	com/google/android/apps/plus/service/EsSyncAdapterService:d	Landroid/os/PowerManager$WakeLock;
    //   312: astore 5
    //   314: aload 5
    //   316: ifnull +9 -> 325
    //   319: getstatic 79	com/google/android/apps/plus/service/EsSyncAdapterService:d	Landroid/os/PowerManager$WakeLock;
    //   322: invokevirtual 84	android/os/PowerManager$WakeLock:release	()V
    //   325: aload_3
    //   326: monitorexit
    //   327: aload_2
    //   328: athrow
    //   329: astore 15
    //   331: ldc 60
    //   333: ldc 142
    //   335: aload 15
    //   337: invokestatic 72	android/util/Log:e	(Ljava/lang/String;Ljava/lang/String;Ljava/lang/Throwable;)I
    //   340: pop
    //   341: goto -185 -> 156
    //   344: astore 13
    //   346: aload 12
    //   348: monitorexit
    //   349: aload 13
    //   351: athrow
    //   352: astore 6
    //   354: ldc 60
    //   356: ldc 142
    //   358: aload 6
    //   360: invokestatic 72	android/util/Log:e	(Ljava/lang/String;Ljava/lang/String;Ljava/lang/Throwable;)I
    //   363: pop
    //   364: goto -39 -> 325
    //   367: astore 4
    //   369: aload_3
    //   370: monitorexit
    //   371: aload 4
    //   373: athrow
    // Local variable table:
    //   start	length	slot	name	signature
    //   0	374	0	this	MandatorySyncService
    //   0	374	1	paramIntent	android.content.Intent
    //   302	26	2	localObject1	java.lang.Object
    //   367	5	4	localObject3	java.lang.Object
    //   312	3	5	localWakeLock1	android.os.PowerManager.WakeLock
    //   352	7	6	localThrowable1	java.lang.Throwable
    //   9	35	8	localgjm	gjm
    //   20	141	9	localgiz	giz
    //   31	3	10	localilb	ilb
    //   110	17	11	localgjo	gjo
    //   135	212	12	localObject4	java.lang.Object
    //   344	6	13	localObject5	java.lang.Object
    //   143	3	14	localWakeLock2	android.os.PowerManager.WakeLock
    //   329	7	15	localThrowable2	java.lang.Throwable
    //   50	18	18	arrayOfgjj	gjj[]
    //   55	10	19	i	int
    //   58	47	20	j	int
    //   75	149	21	str	java.lang.String
    //   287	7	22	localException	java.lang.Exception
    //   86	77	24	k	int
    //   97	3	25	bool	boolean
    //   169	39	26	localgjb	gjb
    //   230	50	27	localAccount	android.accounts.Account
    //   249	25	28	localBundle	android.os.Bundle
    // Exception table:
    //   from	to	target	type
    //   33	52	110	gjo
    //   77	99	287	java/lang/Exception
    //   160	207	287	java/lang/Exception
    //   207	284	287	java/lang/Exception
    //   0	33	302	finally
    //   33	52	302	finally
    //   52	57	302	finally
    //   67	77	302	finally
    //   77	99	302	finally
    //   112	132	302	finally
    //   160	207	302	finally
    //   207	284	302	finally
    //   289	299	302	finally
    //   150	156	329	java/lang/Throwable
    //   140	145	344	finally
    //   150	156	344	finally
    //   156	159	344	finally
    //   331	341	344	finally
    //   346	349	344	finally
    //   319	325	352	java/lang/Throwable
    //   309	314	367	finally
    //   319	325	367	finally
    //   325	327	367	finally
    //   354	364	367	finally
    //   369	371	367	finally
  }
}


/* Location:           F:\apktool\apktool\com.google.android.apps.plus\classes-dex2jar.jar
 * Qualified Name:     com.google.android.apps.plus.service.EsSyncAdapterService.MandatorySyncService
 * JD-Core Version:    0.7.0.1
 */