import android.os.IBinder;
import android.os.Parcel;

final class ewe
  implements ewc
{
  private IBinder a;
  
  ewe(IBinder paramIBinder)
  {
    this.a = paramIBinder;
  }
  
  public final void a()
  {
    Parcel localParcel1 = Parcel.obtain();
    Parcel localParcel2 = Parcel.obtain();
    try
    {
      localParcel1.writeInterfaceToken("com.google.android.gms.googlehelp.internal.common.IGoogleHelpCallbacks");
      this.a.transact(3, localParcel1, localParcel2, 0);
      localParcel2.readException();
      return;
    }
    finally
    {
      localParcel2.recycle();
      localParcel1.recycle();
    }
  }
  
  /* Error */
  public final void a(com.google.android.gms.googlehelp.GoogleHelp paramGoogleHelp)
  {
    // Byte code:
    //   0: invokestatic 21	android/os/Parcel:obtain	()Landroid/os/Parcel;
    //   3: astore_2
    //   4: invokestatic 21	android/os/Parcel:obtain	()Landroid/os/Parcel;
    //   7: astore_3
    //   8: aload_2
    //   9: ldc 23
    //   11: invokevirtual 27	android/os/Parcel:writeInterfaceToken	(Ljava/lang/String;)V
    //   14: aload_1
    //   15: ifnull +41 -> 56
    //   18: aload_2
    //   19: iconst_1
    //   20: invokevirtual 44	android/os/Parcel:writeInt	(I)V
    //   23: aload_1
    //   24: aload_2
    //   25: iconst_0
    //   26: invokevirtual 50	com/google/android/gms/googlehelp/GoogleHelp:writeToParcel	(Landroid/os/Parcel;I)V
    //   29: aload_0
    //   30: getfield 15	ewe:a	Landroid/os/IBinder;
    //   33: iconst_1
    //   34: aload_2
    //   35: aload_3
    //   36: iconst_0
    //   37: invokeinterface 33 5 0
    //   42: pop
    //   43: aload_3
    //   44: invokevirtual 36	android/os/Parcel:readException	()V
    //   47: aload_3
    //   48: invokevirtual 39	android/os/Parcel:recycle	()V
    //   51: aload_2
    //   52: invokevirtual 39	android/os/Parcel:recycle	()V
    //   55: return
    //   56: aload_2
    //   57: iconst_0
    //   58: invokevirtual 44	android/os/Parcel:writeInt	(I)V
    //   61: goto -32 -> 29
    //   64: astore 4
    //   66: aload_3
    //   67: invokevirtual 39	android/os/Parcel:recycle	()V
    //   70: aload_2
    //   71: invokevirtual 39	android/os/Parcel:recycle	()V
    //   74: aload 4
    //   76: athrow
    // Local variable table:
    //   start	length	slot	name	signature
    //   0	77	0	this	ewe
    //   0	77	1	paramGoogleHelp	com.google.android.gms.googlehelp.GoogleHelp
    //   3	68	2	localParcel1	Parcel
    //   7	60	3	localParcel2	Parcel
    //   64	11	4	localObject	Object
    // Exception table:
    //   from	to	target	type
    //   8	14	64	finally
    //   18	29	64	finally
    //   29	47	64	finally
    //   56	61	64	finally
  }
  
  /* Error */
  public final void a(com.google.android.gms.googlehelp.internal.common.TogglingData paramTogglingData)
  {
    // Byte code:
    //   0: invokestatic 21	android/os/Parcel:obtain	()Landroid/os/Parcel;
    //   3: astore_2
    //   4: invokestatic 21	android/os/Parcel:obtain	()Landroid/os/Parcel;
    //   7: astore_3
    //   8: aload_2
    //   9: ldc 23
    //   11: invokevirtual 27	android/os/Parcel:writeInterfaceToken	(Ljava/lang/String;)V
    //   14: aload_1
    //   15: ifnull +41 -> 56
    //   18: aload_2
    //   19: iconst_1
    //   20: invokevirtual 44	android/os/Parcel:writeInt	(I)V
    //   23: aload_1
    //   24: aload_2
    //   25: iconst_0
    //   26: invokevirtual 54	com/google/android/gms/googlehelp/internal/common/TogglingData:writeToParcel	(Landroid/os/Parcel;I)V
    //   29: aload_0
    //   30: getfield 15	ewe:a	Landroid/os/IBinder;
    //   33: iconst_2
    //   34: aload_2
    //   35: aload_3
    //   36: iconst_0
    //   37: invokeinterface 33 5 0
    //   42: pop
    //   43: aload_3
    //   44: invokevirtual 36	android/os/Parcel:readException	()V
    //   47: aload_3
    //   48: invokevirtual 39	android/os/Parcel:recycle	()V
    //   51: aload_2
    //   52: invokevirtual 39	android/os/Parcel:recycle	()V
    //   55: return
    //   56: aload_2
    //   57: iconst_0
    //   58: invokevirtual 44	android/os/Parcel:writeInt	(I)V
    //   61: goto -32 -> 29
    //   64: astore 4
    //   66: aload_3
    //   67: invokevirtual 39	android/os/Parcel:recycle	()V
    //   70: aload_2
    //   71: invokevirtual 39	android/os/Parcel:recycle	()V
    //   74: aload 4
    //   76: athrow
    // Local variable table:
    //   start	length	slot	name	signature
    //   0	77	0	this	ewe
    //   0	77	1	paramTogglingData	com.google.android.gms.googlehelp.internal.common.TogglingData
    //   3	68	2	localParcel1	Parcel
    //   7	60	3	localParcel2	Parcel
    //   64	11	4	localObject	Object
    // Exception table:
    //   from	to	target	type
    //   8	14	64	finally
    //   18	29	64	finally
    //   29	47	64	finally
    //   56	61	64	finally
  }
  
  public final IBinder asBinder()
  {
    return this.a;
  }
  
  public final void b()
  {
    Parcel localParcel1 = Parcel.obtain();
    Parcel localParcel2 = Parcel.obtain();
    try
    {
      localParcel1.writeInterfaceToken("com.google.android.gms.googlehelp.internal.common.IGoogleHelpCallbacks");
      this.a.transact(4, localParcel1, localParcel2, 0);
      localParcel2.readException();
      return;
    }
    finally
    {
      localParcel2.recycle();
      localParcel1.recycle();
    }
  }
  
  public final void c()
  {
    Parcel localParcel1 = Parcel.obtain();
    Parcel localParcel2 = Parcel.obtain();
    try
    {
      localParcel1.writeInterfaceToken("com.google.android.gms.googlehelp.internal.common.IGoogleHelpCallbacks");
      this.a.transact(5, localParcel1, localParcel2, 0);
      localParcel2.readException();
      return;
    }
    finally
    {
      localParcel2.recycle();
      localParcel1.recycle();
    }
  }
  
  public final void d()
  {
    Parcel localParcel1 = Parcel.obtain();
    Parcel localParcel2 = Parcel.obtain();
    try
    {
      localParcel1.writeInterfaceToken("com.google.android.gms.googlehelp.internal.common.IGoogleHelpCallbacks");
      this.a.transact(6, localParcel1, localParcel2, 0);
      localParcel2.readException();
      return;
    }
    finally
    {
      localParcel2.recycle();
      localParcel1.recycle();
    }
  }
}


/* Location:           F:\apktool\apktool\com.google.android.apps.plus\classes-dex2jar.jar
 * Qualified Name:     ewe
 * JD-Core Version:    0.7.0.1
 */