import android.os.IBinder;
import android.os.Parcel;
import com.google.android.gms.herrevad.NetworkQualityReport;

final class exe
  implements exc
{
  private IBinder a;
  
  exe(IBinder paramIBinder)
  {
    this.a = paramIBinder;
  }
  
  /* Error */
  public final void a(NetworkQualityReport paramNetworkQualityReport)
  {
    // Byte code:
    //   0: invokestatic 22	android/os/Parcel:obtain	()Landroid/os/Parcel;
    //   3: astore_2
    //   4: invokestatic 22	android/os/Parcel:obtain	()Landroid/os/Parcel;
    //   7: astore_3
    //   8: aload_2
    //   9: ldc 24
    //   11: invokevirtual 28	android/os/Parcel:writeInterfaceToken	(Ljava/lang/String;)V
    //   14: aload_1
    //   15: ifnull +41 -> 56
    //   18: aload_2
    //   19: iconst_1
    //   20: invokevirtual 32	android/os/Parcel:writeInt	(I)V
    //   23: aload_1
    //   24: aload_2
    //   25: iconst_0
    //   26: invokevirtual 38	com/google/android/gms/herrevad/NetworkQualityReport:writeToParcel	(Landroid/os/Parcel;I)V
    //   29: aload_0
    //   30: getfield 15	exe:a	Landroid/os/IBinder;
    //   33: iconst_1
    //   34: aload_2
    //   35: aload_3
    //   36: iconst_0
    //   37: invokeinterface 44 5 0
    //   42: pop
    //   43: aload_3
    //   44: invokevirtual 47	android/os/Parcel:readException	()V
    //   47: aload_3
    //   48: invokevirtual 50	android/os/Parcel:recycle	()V
    //   51: aload_2
    //   52: invokevirtual 50	android/os/Parcel:recycle	()V
    //   55: return
    //   56: aload_2
    //   57: iconst_0
    //   58: invokevirtual 32	android/os/Parcel:writeInt	(I)V
    //   61: goto -32 -> 29
    //   64: astore 4
    //   66: aload_3
    //   67: invokevirtual 50	android/os/Parcel:recycle	()V
    //   70: aload_2
    //   71: invokevirtual 50	android/os/Parcel:recycle	()V
    //   74: aload 4
    //   76: athrow
    // Local variable table:
    //   start	length	slot	name	signature
    //   0	77	0	this	exe
    //   0	77	1	paramNetworkQualityReport	NetworkQualityReport
    //   3	68	2	localParcel1	Parcel
    //   7	60	3	localParcel2	Parcel
    //   64	11	4	localObject	Object
    // Exception table:
    //   from	to	target	type
    //   8	14	64	finally
    //   18	29	64	finally
    //   29	47	64	finally
    //   56	61	64	finally
  }
  
  public final void a(NetworkQualityReport paramNetworkQualityReport, String paramString1, String paramString2, boolean paramBoolean)
  {
    int i = 1;
    Parcel localParcel1 = Parcel.obtain();
    Parcel localParcel2 = Parcel.obtain();
    for (;;)
    {
      try
      {
        localParcel1.writeInterfaceToken("com.google.android.gms.herrevad.internal.ILightweightNetworkQualityService");
        if (paramNetworkQualityReport != null)
        {
          localParcel1.writeInt(1);
          paramNetworkQualityReport.writeToParcel(localParcel1, 0);
          localParcel1.writeString(paramString1);
          localParcel1.writeString(paramString2);
          if (paramBoolean)
          {
            localParcel1.writeInt(i);
            this.a.transact(3, localParcel1, localParcel2, 0);
            localParcel2.readException();
          }
        }
        else
        {
          localParcel1.writeInt(0);
          continue;
        }
        i = 0;
      }
      finally
      {
        localParcel2.recycle();
        localParcel1.recycle();
      }
    }
  }
  
  /* Error */
  public final void a(ewz paramewz)
  {
    // Byte code:
    //   0: invokestatic 22	android/os/Parcel:obtain	()Landroid/os/Parcel;
    //   3: astore_2
    //   4: invokestatic 22	android/os/Parcel:obtain	()Landroid/os/Parcel;
    //   7: astore_3
    //   8: aload_2
    //   9: ldc 24
    //   11: invokevirtual 28	android/os/Parcel:writeInterfaceToken	(Ljava/lang/String;)V
    //   14: aload_1
    //   15: ifnull +44 -> 59
    //   18: aload_1
    //   19: invokeinterface 61 1 0
    //   24: astore 5
    //   26: aload_2
    //   27: aload 5
    //   29: invokevirtual 64	android/os/Parcel:writeStrongBinder	(Landroid/os/IBinder;)V
    //   32: aload_0
    //   33: getfield 15	exe:a	Landroid/os/IBinder;
    //   36: iconst_2
    //   37: aload_2
    //   38: aload_3
    //   39: iconst_0
    //   40: invokeinterface 44 5 0
    //   45: pop
    //   46: aload_3
    //   47: invokevirtual 47	android/os/Parcel:readException	()V
    //   50: aload_3
    //   51: invokevirtual 50	android/os/Parcel:recycle	()V
    //   54: aload_2
    //   55: invokevirtual 50	android/os/Parcel:recycle	()V
    //   58: return
    //   59: aconst_null
    //   60: astore 5
    //   62: goto -36 -> 26
    //   65: astore 4
    //   67: aload_3
    //   68: invokevirtual 50	android/os/Parcel:recycle	()V
    //   71: aload_2
    //   72: invokevirtual 50	android/os/Parcel:recycle	()V
    //   75: aload 4
    //   77: athrow
    // Local variable table:
    //   start	length	slot	name	signature
    //   0	78	0	this	exe
    //   0	78	1	paramewz	ewz
    //   3	69	2	localParcel1	Parcel
    //   7	61	3	localParcel2	Parcel
    //   65	11	4	localObject	Object
    //   24	37	5	localIBinder	IBinder
    // Exception table:
    //   from	to	target	type
    //   8	14	65	finally
    //   18	26	65	finally
    //   26	50	65	finally
  }
  
  public final IBinder asBinder()
  {
    return this.a;
  }
}


/* Location:           F:\apktool\apktool\com.google.android.apps.plus\classes-dex2jar.jar
 * Qualified Name:     exe
 * JD-Core Version:    0.7.0.1
 */