import android.os.Bundle;
import android.os.IBinder;
import android.os.Parcel;

public final class fae
  implements fac
{
  private IBinder a;
  
  public fae(IBinder paramIBinder)
  {
    this.a = paramIBinder;
  }
  
  /* Error */
  public final void a(exh paramexh)
  {
    // Byte code:
    //   0: invokestatic 22	android/os/Parcel:obtain	()Landroid/os/Parcel;
    //   3: astore_2
    //   4: invokestatic 22	android/os/Parcel:obtain	()Landroid/os/Parcel;
    //   7: astore_3
    //   8: aload_2
    //   9: ldc 24
    //   11: invokevirtual 28	android/os/Parcel:writeInterfaceToken	(Ljava/lang/String;)V
    //   14: aload_1
    //   15: ifnull +44 -> 59
    //   18: aload_1
    //   19: invokeinterface 34 1 0
    //   24: astore 5
    //   26: aload_2
    //   27: aload 5
    //   29: invokevirtual 37	android/os/Parcel:writeStrongBinder	(Landroid/os/IBinder;)V
    //   32: aload_0
    //   33: getfield 15	fae:a	Landroid/os/IBinder;
    //   36: iconst_2
    //   37: aload_2
    //   38: aload_3
    //   39: iconst_0
    //   40: invokeinterface 43 5 0
    //   45: pop
    //   46: aload_3
    //   47: invokevirtual 46	android/os/Parcel:readException	()V
    //   50: aload_3
    //   51: invokevirtual 49	android/os/Parcel:recycle	()V
    //   54: aload_2
    //   55: invokevirtual 49	android/os/Parcel:recycle	()V
    //   58: return
    //   59: aconst_null
    //   60: astore 5
    //   62: goto -36 -> 26
    //   65: astore 4
    //   67: aload_3
    //   68: invokevirtual 49	android/os/Parcel:recycle	()V
    //   71: aload_2
    //   72: invokevirtual 49	android/os/Parcel:recycle	()V
    //   75: aload 4
    //   77: athrow
    // Local variable table:
    //   start	length	slot	name	signature
    //   0	78	0	this	fae
    //   0	78	1	paramexh	exh
    //   3	69	2	localParcel1	Parcel
    //   7	61	3	localParcel2	Parcel
    //   65	11	4	localObject	Object
    //   24	37	5	localIBinder	IBinder
    // Exception table:
    //   from	to	target	type
    //   8	14	65	finally
    //   18	26	65	finally
    //   26	50	65	finally
  }
  
  /* Error */
  public final void a(exk paramexk)
  {
    // Byte code:
    //   0: invokestatic 22	android/os/Parcel:obtain	()Landroid/os/Parcel;
    //   3: astore_2
    //   4: invokestatic 22	android/os/Parcel:obtain	()Landroid/os/Parcel;
    //   7: astore_3
    //   8: aload_2
    //   9: ldc 24
    //   11: invokevirtual 28	android/os/Parcel:writeInterfaceToken	(Ljava/lang/String;)V
    //   14: aload_1
    //   15: ifnull +44 -> 59
    //   18: aload_1
    //   19: invokeinterface 53 1 0
    //   24: astore 5
    //   26: aload_2
    //   27: aload 5
    //   29: invokevirtual 37	android/os/Parcel:writeStrongBinder	(Landroid/os/IBinder;)V
    //   32: aload_0
    //   33: getfield 15	fae:a	Landroid/os/IBinder;
    //   36: iconst_3
    //   37: aload_2
    //   38: aload_3
    //   39: iconst_0
    //   40: invokeinterface 43 5 0
    //   45: pop
    //   46: aload_3
    //   47: invokevirtual 46	android/os/Parcel:readException	()V
    //   50: aload_3
    //   51: invokevirtual 49	android/os/Parcel:recycle	()V
    //   54: aload_2
    //   55: invokevirtual 49	android/os/Parcel:recycle	()V
    //   58: return
    //   59: aconst_null
    //   60: astore 5
    //   62: goto -36 -> 26
    //   65: astore 4
    //   67: aload_3
    //   68: invokevirtual 49	android/os/Parcel:recycle	()V
    //   71: aload_2
    //   72: invokevirtual 49	android/os/Parcel:recycle	()V
    //   75: aload 4
    //   77: athrow
    // Local variable table:
    //   start	length	slot	name	signature
    //   0	78	0	this	fae
    //   0	78	1	paramexk	exk
    //   3	69	2	localParcel1	Parcel
    //   7	61	3	localParcel2	Parcel
    //   65	11	4	localObject	Object
    //   24	37	5	localIBinder	IBinder
    // Exception table:
    //   from	to	target	type
    //   8	14	65	finally
    //   18	26	65	finally
    //   26	50	65	finally
  }
  
  public final void a(String paramString, Bundle paramBundle1, Bundle paramBundle2)
  {
    Parcel localParcel1 = Parcel.obtain();
    Parcel localParcel2 = Parcel.obtain();
    for (;;)
    {
      try
      {
        localParcel1.writeInterfaceToken("com.google.android.gms.mdm.internal.INetworkQualityService");
        localParcel1.writeString(paramString);
        if (paramBundle1 != null)
        {
          localParcel1.writeInt(1);
          paramBundle1.writeToParcel(localParcel1, 0);
          if (paramBundle2 != null)
          {
            localParcel1.writeInt(1);
            paramBundle2.writeToParcel(localParcel1, 0);
            this.a.transact(1, localParcel1, localParcel2, 0);
            localParcel2.readException();
          }
        }
        else
        {
          localParcel1.writeInt(0);
          continue;
        }
        localParcel1.writeInt(0);
      }
      finally
      {
        localParcel2.recycle();
        localParcel1.recycle();
      }
    }
  }
  
  public final IBinder asBinder()
  {
    return this.a;
  }
}


/* Location:           F:\apktool\apktool\com.google.android.apps.plus\classes-dex2jar.jar
 * Qualified Name:     fae
 * JD-Core Version:    0.7.0.1
 */