import android.os.IBinder;

final class fbt
  implements fbr
{
  private IBinder a;
  
  fbt(IBinder paramIBinder)
  {
    this.a = paramIBinder;
  }
  
  /* Error */
  public final void a(fbo paramfbo)
  {
    // Byte code:
    //   0: invokestatic 22	android/os/Parcel:obtain	()Landroid/os/Parcel;
    //   3: astore_2
    //   4: invokestatic 22	android/os/Parcel:obtain	()Landroid/os/Parcel;
    //   7: astore_3
    //   8: aload_2
    //   9: ldc 24
    //   11: invokevirtual 28	android/os/Parcel:writeInterfaceToken	(Ljava/lang/String;)V
    //   14: aload_1
    //   15: ifnull +44 -> 59
    //   18: aload_1
    //   19: invokeinterface 34 1 0
    //   24: astore 5
    //   26: aload_2
    //   27: aload 5
    //   29: invokevirtual 37	android/os/Parcel:writeStrongBinder	(Landroid/os/IBinder;)V
    //   32: aload_0
    //   33: getfield 15	fbt:a	Landroid/os/IBinder;
    //   36: iconst_1
    //   37: aload_2
    //   38: aload_3
    //   39: iconst_0
    //   40: invokeinterface 43 5 0
    //   45: pop
    //   46: aload_3
    //   47: invokevirtual 46	android/os/Parcel:readException	()V
    //   50: aload_3
    //   51: invokevirtual 49	android/os/Parcel:recycle	()V
    //   54: aload_2
    //   55: invokevirtual 49	android/os/Parcel:recycle	()V
    //   58: return
    //   59: aconst_null
    //   60: astore 5
    //   62: goto -36 -> 26
    //   65: astore 4
    //   67: aload_3
    //   68: invokevirtual 49	android/os/Parcel:recycle	()V
    //   71: aload_2
    //   72: invokevirtual 49	android/os/Parcel:recycle	()V
    //   75: aload 4
    //   77: athrow
    // Local variable table:
    //   start	length	slot	name	signature
    //   0	78	0	this	fbt
    //   0	78	1	paramfbo	fbo
    //   3	69	2	localParcel1	android.os.Parcel
    //   7	61	3	localParcel2	android.os.Parcel
    //   65	11	4	localObject	Object
    //   24	37	5	localIBinder	IBinder
    // Exception table:
    //   from	to	target	type
    //   8	14	65	finally
    //   18	26	65	finally
    //   26	50	65	finally
  }
  
  /* Error */
  public final void a(fbo paramfbo, com.google.android.gms.photos.autobackup.model.AutoBackupSettings paramAutoBackupSettings)
  {
    // Byte code:
    //   0: invokestatic 22	android/os/Parcel:obtain	()Landroid/os/Parcel;
    //   3: astore_3
    //   4: invokestatic 22	android/os/Parcel:obtain	()Landroid/os/Parcel;
    //   7: astore 4
    //   9: aload_3
    //   10: ldc 24
    //   12: invokevirtual 28	android/os/Parcel:writeInterfaceToken	(Ljava/lang/String;)V
    //   15: aload_1
    //   16: ifnull +63 -> 79
    //   19: aload_1
    //   20: invokeinterface 34 1 0
    //   25: astore 6
    //   27: aload_3
    //   28: aload 6
    //   30: invokevirtual 37	android/os/Parcel:writeStrongBinder	(Landroid/os/IBinder;)V
    //   33: aload_2
    //   34: ifnull +51 -> 85
    //   37: aload_3
    //   38: iconst_1
    //   39: invokevirtual 54	android/os/Parcel:writeInt	(I)V
    //   42: aload_2
    //   43: aload_3
    //   44: iconst_0
    //   45: invokevirtual 60	com/google/android/gms/photos/autobackup/model/AutoBackupSettings:writeToParcel	(Landroid/os/Parcel;I)V
    //   48: aload_0
    //   49: getfield 15	fbt:a	Landroid/os/IBinder;
    //   52: bipush 9
    //   54: aload_3
    //   55: aload 4
    //   57: iconst_0
    //   58: invokeinterface 43 5 0
    //   63: pop
    //   64: aload 4
    //   66: invokevirtual 46	android/os/Parcel:readException	()V
    //   69: aload 4
    //   71: invokevirtual 49	android/os/Parcel:recycle	()V
    //   74: aload_3
    //   75: invokevirtual 49	android/os/Parcel:recycle	()V
    //   78: return
    //   79: aconst_null
    //   80: astore 6
    //   82: goto -55 -> 27
    //   85: aload_3
    //   86: iconst_0
    //   87: invokevirtual 54	android/os/Parcel:writeInt	(I)V
    //   90: goto -42 -> 48
    //   93: astore 5
    //   95: aload 4
    //   97: invokevirtual 49	android/os/Parcel:recycle	()V
    //   100: aload_3
    //   101: invokevirtual 49	android/os/Parcel:recycle	()V
    //   104: aload 5
    //   106: athrow
    // Local variable table:
    //   start	length	slot	name	signature
    //   0	107	0	this	fbt
    //   0	107	1	paramfbo	fbo
    //   0	107	2	paramAutoBackupSettings	com.google.android.gms.photos.autobackup.model.AutoBackupSettings
    //   3	98	3	localParcel1	android.os.Parcel
    //   7	89	4	localParcel2	android.os.Parcel
    //   93	12	5	localObject	Object
    //   25	56	6	localIBinder	IBinder
    // Exception table:
    //   from	to	target	type
    //   9	15	93	finally
    //   19	27	93	finally
    //   27	33	93	finally
    //   37	48	93	finally
    //   48	69	93	finally
    //   85	90	93	finally
  }
  
  /* Error */
  public final void a(fbo paramfbo, java.lang.String paramString)
  {
    // Byte code:
    //   0: invokestatic 22	android/os/Parcel:obtain	()Landroid/os/Parcel;
    //   3: astore_3
    //   4: invokestatic 22	android/os/Parcel:obtain	()Landroid/os/Parcel;
    //   7: astore 4
    //   9: aload_3
    //   10: ldc 24
    //   12: invokevirtual 28	android/os/Parcel:writeInterfaceToken	(Ljava/lang/String;)V
    //   15: aload_1
    //   16: ifnull +52 -> 68
    //   19: aload_1
    //   20: invokeinterface 34 1 0
    //   25: astore 6
    //   27: aload_3
    //   28: aload 6
    //   30: invokevirtual 37	android/os/Parcel:writeStrongBinder	(Landroid/os/IBinder;)V
    //   33: aload_3
    //   34: aload_2
    //   35: invokevirtual 64	android/os/Parcel:writeString	(Ljava/lang/String;)V
    //   38: aload_0
    //   39: getfield 15	fbt:a	Landroid/os/IBinder;
    //   42: iconst_3
    //   43: aload_3
    //   44: aload 4
    //   46: iconst_0
    //   47: invokeinterface 43 5 0
    //   52: pop
    //   53: aload 4
    //   55: invokevirtual 46	android/os/Parcel:readException	()V
    //   58: aload 4
    //   60: invokevirtual 49	android/os/Parcel:recycle	()V
    //   63: aload_3
    //   64: invokevirtual 49	android/os/Parcel:recycle	()V
    //   67: return
    //   68: aconst_null
    //   69: astore 6
    //   71: goto -44 -> 27
    //   74: astore 5
    //   76: aload 4
    //   78: invokevirtual 49	android/os/Parcel:recycle	()V
    //   81: aload_3
    //   82: invokevirtual 49	android/os/Parcel:recycle	()V
    //   85: aload 5
    //   87: athrow
    // Local variable table:
    //   start	length	slot	name	signature
    //   0	88	0	this	fbt
    //   0	88	1	paramfbo	fbo
    //   0	88	2	paramString	java.lang.String
    //   3	79	3	localParcel1	android.os.Parcel
    //   7	70	4	localParcel2	android.os.Parcel
    //   74	12	5	localObject	Object
    //   25	45	6	localIBinder	IBinder
    // Exception table:
    //   from	to	target	type
    //   9	15	74	finally
    //   19	27	74	finally
    //   27	58	74	finally
  }
  
  /* Error */
  public final void a(fbo paramfbo, java.lang.String paramString, com.google.android.gms.photos.autobackup.model.LocalFolder paramLocalFolder)
  {
    // Byte code:
    //   0: invokestatic 22	android/os/Parcel:obtain	()Landroid/os/Parcel;
    //   3: astore 4
    //   5: invokestatic 22	android/os/Parcel:obtain	()Landroid/os/Parcel;
    //   8: astore 5
    //   10: aload 4
    //   12: ldc 24
    //   14: invokevirtual 28	android/os/Parcel:writeInterfaceToken	(Ljava/lang/String;)V
    //   17: aload_1
    //   18: ifnull +74 -> 92
    //   21: aload_1
    //   22: invokeinterface 34 1 0
    //   27: astore 7
    //   29: aload 4
    //   31: aload 7
    //   33: invokevirtual 37	android/os/Parcel:writeStrongBinder	(Landroid/os/IBinder;)V
    //   36: aload 4
    //   38: aload_2
    //   39: invokevirtual 64	android/os/Parcel:writeString	(Ljava/lang/String;)V
    //   42: aload_3
    //   43: ifnull +55 -> 98
    //   46: aload 4
    //   48: iconst_1
    //   49: invokevirtual 54	android/os/Parcel:writeInt	(I)V
    //   52: aload_3
    //   53: aload 4
    //   55: iconst_0
    //   56: invokevirtual 68	com/google/android/gms/photos/autobackup/model/LocalFolder:writeToParcel	(Landroid/os/Parcel;I)V
    //   59: aload_0
    //   60: getfield 15	fbt:a	Landroid/os/IBinder;
    //   63: bipush 6
    //   65: aload 4
    //   67: aload 5
    //   69: iconst_0
    //   70: invokeinterface 43 5 0
    //   75: pop
    //   76: aload 5
    //   78: invokevirtual 46	android/os/Parcel:readException	()V
    //   81: aload 5
    //   83: invokevirtual 49	android/os/Parcel:recycle	()V
    //   86: aload 4
    //   88: invokevirtual 49	android/os/Parcel:recycle	()V
    //   91: return
    //   92: aconst_null
    //   93: astore 7
    //   95: goto -66 -> 29
    //   98: aload 4
    //   100: iconst_0
    //   101: invokevirtual 54	android/os/Parcel:writeInt	(I)V
    //   104: goto -45 -> 59
    //   107: astore 6
    //   109: aload 5
    //   111: invokevirtual 49	android/os/Parcel:recycle	()V
    //   114: aload 4
    //   116: invokevirtual 49	android/os/Parcel:recycle	()V
    //   119: aload 6
    //   121: athrow
    // Local variable table:
    //   start	length	slot	name	signature
    //   0	122	0	this	fbt
    //   0	122	1	paramfbo	fbo
    //   0	122	2	paramString	java.lang.String
    //   0	122	3	paramLocalFolder	com.google.android.gms.photos.autobackup.model.LocalFolder
    //   3	112	4	localParcel1	android.os.Parcel
    //   8	102	5	localParcel2	android.os.Parcel
    //   107	13	6	localObject	Object
    //   27	67	7	localIBinder	IBinder
    // Exception table:
    //   from	to	target	type
    //   10	17	107	finally
    //   21	29	107	finally
    //   29	42	107	finally
    //   46	59	107	finally
    //   59	81	107	finally
    //   98	104	107	finally
  }
  
  /* Error */
  public final void a(fbo paramfbo, java.lang.String paramString, com.google.android.gms.photos.autobackup.model.SyncSettings paramSyncSettings)
  {
    // Byte code:
    //   0: invokestatic 22	android/os/Parcel:obtain	()Landroid/os/Parcel;
    //   3: astore 4
    //   5: invokestatic 22	android/os/Parcel:obtain	()Landroid/os/Parcel;
    //   8: astore 5
    //   10: aload 4
    //   12: ldc 24
    //   14: invokevirtual 28	android/os/Parcel:writeInterfaceToken	(Ljava/lang/String;)V
    //   17: aload_1
    //   18: ifnull +74 -> 92
    //   21: aload_1
    //   22: invokeinterface 34 1 0
    //   27: astore 7
    //   29: aload 4
    //   31: aload 7
    //   33: invokevirtual 37	android/os/Parcel:writeStrongBinder	(Landroid/os/IBinder;)V
    //   36: aload 4
    //   38: aload_2
    //   39: invokevirtual 64	android/os/Parcel:writeString	(Ljava/lang/String;)V
    //   42: aload_3
    //   43: ifnull +55 -> 98
    //   46: aload 4
    //   48: iconst_1
    //   49: invokevirtual 54	android/os/Parcel:writeInt	(I)V
    //   52: aload_3
    //   53: aload 4
    //   55: iconst_0
    //   56: invokevirtual 72	com/google/android/gms/photos/autobackup/model/SyncSettings:writeToParcel	(Landroid/os/Parcel;I)V
    //   59: aload_0
    //   60: getfield 15	fbt:a	Landroid/os/IBinder;
    //   63: bipush 12
    //   65: aload 4
    //   67: aload 5
    //   69: iconst_0
    //   70: invokeinterface 43 5 0
    //   75: pop
    //   76: aload 5
    //   78: invokevirtual 46	android/os/Parcel:readException	()V
    //   81: aload 5
    //   83: invokevirtual 49	android/os/Parcel:recycle	()V
    //   86: aload 4
    //   88: invokevirtual 49	android/os/Parcel:recycle	()V
    //   91: return
    //   92: aconst_null
    //   93: astore 7
    //   95: goto -66 -> 29
    //   98: aload 4
    //   100: iconst_0
    //   101: invokevirtual 54	android/os/Parcel:writeInt	(I)V
    //   104: goto -45 -> 59
    //   107: astore 6
    //   109: aload 5
    //   111: invokevirtual 49	android/os/Parcel:recycle	()V
    //   114: aload 4
    //   116: invokevirtual 49	android/os/Parcel:recycle	()V
    //   119: aload 6
    //   121: athrow
    // Local variable table:
    //   start	length	slot	name	signature
    //   0	122	0	this	fbt
    //   0	122	1	paramfbo	fbo
    //   0	122	2	paramString	java.lang.String
    //   0	122	3	paramSyncSettings	com.google.android.gms.photos.autobackup.model.SyncSettings
    //   3	112	4	localParcel1	android.os.Parcel
    //   8	102	5	localParcel2	android.os.Parcel
    //   107	13	6	localObject	Object
    //   27	67	7	localIBinder	IBinder
    // Exception table:
    //   from	to	target	type
    //   10	17	107	finally
    //   21	29	107	finally
    //   29	42	107	finally
    //   46	59	107	finally
    //   59	81	107	finally
    //   98	104	107	finally
  }
  
  /* Error */
  public final void a(fbo paramfbo, java.lang.String paramString, java.lang.String[] paramArrayOfString)
  {
    // Byte code:
    //   0: invokestatic 22	android/os/Parcel:obtain	()Landroid/os/Parcel;
    //   3: astore 4
    //   5: invokestatic 22	android/os/Parcel:obtain	()Landroid/os/Parcel;
    //   8: astore 5
    //   10: aload 4
    //   12: ldc 24
    //   14: invokevirtual 28	android/os/Parcel:writeInterfaceToken	(Ljava/lang/String;)V
    //   17: aload_1
    //   18: ifnull +63 -> 81
    //   21: aload_1
    //   22: invokeinterface 34 1 0
    //   27: astore 7
    //   29: aload 4
    //   31: aload 7
    //   33: invokevirtual 37	android/os/Parcel:writeStrongBinder	(Landroid/os/IBinder;)V
    //   36: aload 4
    //   38: aload_2
    //   39: invokevirtual 64	android/os/Parcel:writeString	(Ljava/lang/String;)V
    //   42: aload 4
    //   44: aload_3
    //   45: invokevirtual 77	android/os/Parcel:writeStringArray	([Ljava/lang/String;)V
    //   48: aload_0
    //   49: getfield 15	fbt:a	Landroid/os/IBinder;
    //   52: bipush 14
    //   54: aload 4
    //   56: aload 5
    //   58: iconst_0
    //   59: invokeinterface 43 5 0
    //   64: pop
    //   65: aload 5
    //   67: invokevirtual 46	android/os/Parcel:readException	()V
    //   70: aload 5
    //   72: invokevirtual 49	android/os/Parcel:recycle	()V
    //   75: aload 4
    //   77: invokevirtual 49	android/os/Parcel:recycle	()V
    //   80: return
    //   81: aconst_null
    //   82: astore 7
    //   84: goto -55 -> 29
    //   87: astore 6
    //   89: aload 5
    //   91: invokevirtual 49	android/os/Parcel:recycle	()V
    //   94: aload 4
    //   96: invokevirtual 49	android/os/Parcel:recycle	()V
    //   99: aload 6
    //   101: athrow
    // Local variable table:
    //   start	length	slot	name	signature
    //   0	102	0	this	fbt
    //   0	102	1	paramfbo	fbo
    //   0	102	2	paramString	java.lang.String
    //   0	102	3	paramArrayOfString	java.lang.String[]
    //   3	92	4	localParcel1	android.os.Parcel
    //   8	82	5	localParcel2	android.os.Parcel
    //   87	13	6	localObject	Object
    //   27	56	7	localIBinder	IBinder
    // Exception table:
    //   from	to	target	type
    //   10	17	87	finally
    //   21	29	87	finally
    //   29	70	87	finally
  }
  
  public final IBinder asBinder()
  {
    return this.a;
  }
  
  /* Error */
  public final void b(fbo paramfbo)
  {
    // Byte code:
    //   0: invokestatic 22	android/os/Parcel:obtain	()Landroid/os/Parcel;
    //   3: astore_2
    //   4: invokestatic 22	android/os/Parcel:obtain	()Landroid/os/Parcel;
    //   7: astore_3
    //   8: aload_2
    //   9: ldc 24
    //   11: invokevirtual 28	android/os/Parcel:writeInterfaceToken	(Ljava/lang/String;)V
    //   14: aload_1
    //   15: ifnull +44 -> 59
    //   18: aload_1
    //   19: invokeinterface 34 1 0
    //   24: astore 5
    //   26: aload_2
    //   27: aload 5
    //   29: invokevirtual 37	android/os/Parcel:writeStrongBinder	(Landroid/os/IBinder;)V
    //   32: aload_0
    //   33: getfield 15	fbt:a	Landroid/os/IBinder;
    //   36: iconst_2
    //   37: aload_2
    //   38: aload_3
    //   39: iconst_0
    //   40: invokeinterface 43 5 0
    //   45: pop
    //   46: aload_3
    //   47: invokevirtual 46	android/os/Parcel:readException	()V
    //   50: aload_3
    //   51: invokevirtual 49	android/os/Parcel:recycle	()V
    //   54: aload_2
    //   55: invokevirtual 49	android/os/Parcel:recycle	()V
    //   58: return
    //   59: aconst_null
    //   60: astore 5
    //   62: goto -36 -> 26
    //   65: astore 4
    //   67: aload_3
    //   68: invokevirtual 49	android/os/Parcel:recycle	()V
    //   71: aload_2
    //   72: invokevirtual 49	android/os/Parcel:recycle	()V
    //   75: aload 4
    //   77: athrow
    // Local variable table:
    //   start	length	slot	name	signature
    //   0	78	0	this	fbt
    //   0	78	1	paramfbo	fbo
    //   3	69	2	localParcel1	android.os.Parcel
    //   7	61	3	localParcel2	android.os.Parcel
    //   65	11	4	localObject	Object
    //   24	37	5	localIBinder	IBinder
    // Exception table:
    //   from	to	target	type
    //   8	14	65	finally
    //   18	26	65	finally
    //   26	50	65	finally
  }
  
  /* Error */
  public final void b(fbo paramfbo, java.lang.String paramString)
  {
    // Byte code:
    //   0: invokestatic 22	android/os/Parcel:obtain	()Landroid/os/Parcel;
    //   3: astore_3
    //   4: invokestatic 22	android/os/Parcel:obtain	()Landroid/os/Parcel;
    //   7: astore 4
    //   9: aload_3
    //   10: ldc 24
    //   12: invokevirtual 28	android/os/Parcel:writeInterfaceToken	(Ljava/lang/String;)V
    //   15: aload_1
    //   16: ifnull +52 -> 68
    //   19: aload_1
    //   20: invokeinterface 34 1 0
    //   25: astore 6
    //   27: aload_3
    //   28: aload 6
    //   30: invokevirtual 37	android/os/Parcel:writeStrongBinder	(Landroid/os/IBinder;)V
    //   33: aload_3
    //   34: aload_2
    //   35: invokevirtual 64	android/os/Parcel:writeString	(Ljava/lang/String;)V
    //   38: aload_0
    //   39: getfield 15	fbt:a	Landroid/os/IBinder;
    //   42: iconst_5
    //   43: aload_3
    //   44: aload 4
    //   46: iconst_0
    //   47: invokeinterface 43 5 0
    //   52: pop
    //   53: aload 4
    //   55: invokevirtual 46	android/os/Parcel:readException	()V
    //   58: aload 4
    //   60: invokevirtual 49	android/os/Parcel:recycle	()V
    //   63: aload_3
    //   64: invokevirtual 49	android/os/Parcel:recycle	()V
    //   67: return
    //   68: aconst_null
    //   69: astore 6
    //   71: goto -44 -> 27
    //   74: astore 5
    //   76: aload 4
    //   78: invokevirtual 49	android/os/Parcel:recycle	()V
    //   81: aload_3
    //   82: invokevirtual 49	android/os/Parcel:recycle	()V
    //   85: aload 5
    //   87: athrow
    // Local variable table:
    //   start	length	slot	name	signature
    //   0	88	0	this	fbt
    //   0	88	1	paramfbo	fbo
    //   0	88	2	paramString	java.lang.String
    //   3	79	3	localParcel1	android.os.Parcel
    //   7	70	4	localParcel2	android.os.Parcel
    //   74	12	5	localObject	Object
    //   25	45	6	localIBinder	IBinder
    // Exception table:
    //   from	to	target	type
    //   9	15	74	finally
    //   19	27	74	finally
    //   27	58	74	finally
  }
  
  /* Error */
  public final void c(fbo paramfbo)
  {
    // Byte code:
    //   0: invokestatic 22	android/os/Parcel:obtain	()Landroid/os/Parcel;
    //   3: astore_2
    //   4: invokestatic 22	android/os/Parcel:obtain	()Landroid/os/Parcel;
    //   7: astore_3
    //   8: aload_2
    //   9: ldc 24
    //   11: invokevirtual 28	android/os/Parcel:writeInterfaceToken	(Ljava/lang/String;)V
    //   14: aload_1
    //   15: ifnull +44 -> 59
    //   18: aload_1
    //   19: invokeinterface 34 1 0
    //   24: astore 5
    //   26: aload_2
    //   27: aload 5
    //   29: invokevirtual 37	android/os/Parcel:writeStrongBinder	(Landroid/os/IBinder;)V
    //   32: aload_0
    //   33: getfield 15	fbt:a	Landroid/os/IBinder;
    //   36: iconst_4
    //   37: aload_2
    //   38: aload_3
    //   39: iconst_0
    //   40: invokeinterface 43 5 0
    //   45: pop
    //   46: aload_3
    //   47: invokevirtual 46	android/os/Parcel:readException	()V
    //   50: aload_3
    //   51: invokevirtual 49	android/os/Parcel:recycle	()V
    //   54: aload_2
    //   55: invokevirtual 49	android/os/Parcel:recycle	()V
    //   58: return
    //   59: aconst_null
    //   60: astore 5
    //   62: goto -36 -> 26
    //   65: astore 4
    //   67: aload_3
    //   68: invokevirtual 49	android/os/Parcel:recycle	()V
    //   71: aload_2
    //   72: invokevirtual 49	android/os/Parcel:recycle	()V
    //   75: aload 4
    //   77: athrow
    // Local variable table:
    //   start	length	slot	name	signature
    //   0	78	0	this	fbt
    //   0	78	1	paramfbo	fbo
    //   3	69	2	localParcel1	android.os.Parcel
    //   7	61	3	localParcel2	android.os.Parcel
    //   65	11	4	localObject	Object
    //   24	37	5	localIBinder	IBinder
    // Exception table:
    //   from	to	target	type
    //   8	14	65	finally
    //   18	26	65	finally
    //   26	50	65	finally
  }
  
  /* Error */
  public final void c(fbo paramfbo, java.lang.String paramString)
  {
    // Byte code:
    //   0: invokestatic 22	android/os/Parcel:obtain	()Landroid/os/Parcel;
    //   3: astore_3
    //   4: invokestatic 22	android/os/Parcel:obtain	()Landroid/os/Parcel;
    //   7: astore 4
    //   9: aload_3
    //   10: ldc 24
    //   12: invokevirtual 28	android/os/Parcel:writeInterfaceToken	(Ljava/lang/String;)V
    //   15: aload_1
    //   16: ifnull +53 -> 69
    //   19: aload_1
    //   20: invokeinterface 34 1 0
    //   25: astore 6
    //   27: aload_3
    //   28: aload 6
    //   30: invokevirtual 37	android/os/Parcel:writeStrongBinder	(Landroid/os/IBinder;)V
    //   33: aload_3
    //   34: aload_2
    //   35: invokevirtual 64	android/os/Parcel:writeString	(Ljava/lang/String;)V
    //   38: aload_0
    //   39: getfield 15	fbt:a	Landroid/os/IBinder;
    //   42: bipush 7
    //   44: aload_3
    //   45: aload 4
    //   47: iconst_0
    //   48: invokeinterface 43 5 0
    //   53: pop
    //   54: aload 4
    //   56: invokevirtual 46	android/os/Parcel:readException	()V
    //   59: aload 4
    //   61: invokevirtual 49	android/os/Parcel:recycle	()V
    //   64: aload_3
    //   65: invokevirtual 49	android/os/Parcel:recycle	()V
    //   68: return
    //   69: aconst_null
    //   70: astore 6
    //   72: goto -45 -> 27
    //   75: astore 5
    //   77: aload 4
    //   79: invokevirtual 49	android/os/Parcel:recycle	()V
    //   82: aload_3
    //   83: invokevirtual 49	android/os/Parcel:recycle	()V
    //   86: aload 5
    //   88: athrow
    // Local variable table:
    //   start	length	slot	name	signature
    //   0	89	0	this	fbt
    //   0	89	1	paramfbo	fbo
    //   0	89	2	paramString	java.lang.String
    //   3	80	3	localParcel1	android.os.Parcel
    //   7	71	4	localParcel2	android.os.Parcel
    //   75	12	5	localObject	Object
    //   25	46	6	localIBinder	IBinder
    // Exception table:
    //   from	to	target	type
    //   9	15	75	finally
    //   19	27	75	finally
    //   27	59	75	finally
  }
  
  /* Error */
  public final void d(fbo paramfbo)
  {
    // Byte code:
    //   0: invokestatic 22	android/os/Parcel:obtain	()Landroid/os/Parcel;
    //   3: astore_2
    //   4: invokestatic 22	android/os/Parcel:obtain	()Landroid/os/Parcel;
    //   7: astore_3
    //   8: aload_2
    //   9: ldc 24
    //   11: invokevirtual 28	android/os/Parcel:writeInterfaceToken	(Ljava/lang/String;)V
    //   14: aload_1
    //   15: ifnull +45 -> 60
    //   18: aload_1
    //   19: invokeinterface 34 1 0
    //   24: astore 5
    //   26: aload_2
    //   27: aload 5
    //   29: invokevirtual 37	android/os/Parcel:writeStrongBinder	(Landroid/os/IBinder;)V
    //   32: aload_0
    //   33: getfield 15	fbt:a	Landroid/os/IBinder;
    //   36: bipush 8
    //   38: aload_2
    //   39: aload_3
    //   40: iconst_0
    //   41: invokeinterface 43 5 0
    //   46: pop
    //   47: aload_3
    //   48: invokevirtual 46	android/os/Parcel:readException	()V
    //   51: aload_3
    //   52: invokevirtual 49	android/os/Parcel:recycle	()V
    //   55: aload_2
    //   56: invokevirtual 49	android/os/Parcel:recycle	()V
    //   59: return
    //   60: aconst_null
    //   61: astore 5
    //   63: goto -37 -> 26
    //   66: astore 4
    //   68: aload_3
    //   69: invokevirtual 49	android/os/Parcel:recycle	()V
    //   72: aload_2
    //   73: invokevirtual 49	android/os/Parcel:recycle	()V
    //   76: aload 4
    //   78: athrow
    // Local variable table:
    //   start	length	slot	name	signature
    //   0	79	0	this	fbt
    //   0	79	1	paramfbo	fbo
    //   3	70	2	localParcel1	android.os.Parcel
    //   7	62	3	localParcel2	android.os.Parcel
    //   66	11	4	localObject	Object
    //   24	38	5	localIBinder	IBinder
    // Exception table:
    //   from	to	target	type
    //   8	14	66	finally
    //   18	26	66	finally
    //   26	51	66	finally
  }
  
  /* Error */
  public final void d(fbo paramfbo, java.lang.String paramString)
  {
    // Byte code:
    //   0: invokestatic 22	android/os/Parcel:obtain	()Landroid/os/Parcel;
    //   3: astore_3
    //   4: invokestatic 22	android/os/Parcel:obtain	()Landroid/os/Parcel;
    //   7: astore 4
    //   9: aload_3
    //   10: ldc 24
    //   12: invokevirtual 28	android/os/Parcel:writeInterfaceToken	(Ljava/lang/String;)V
    //   15: aload_1
    //   16: ifnull +53 -> 69
    //   19: aload_1
    //   20: invokeinterface 34 1 0
    //   25: astore 6
    //   27: aload_3
    //   28: aload 6
    //   30: invokevirtual 37	android/os/Parcel:writeStrongBinder	(Landroid/os/IBinder;)V
    //   33: aload_3
    //   34: aload_2
    //   35: invokevirtual 64	android/os/Parcel:writeString	(Ljava/lang/String;)V
    //   38: aload_0
    //   39: getfield 15	fbt:a	Landroid/os/IBinder;
    //   42: bipush 10
    //   44: aload_3
    //   45: aload 4
    //   47: iconst_0
    //   48: invokeinterface 43 5 0
    //   53: pop
    //   54: aload 4
    //   56: invokevirtual 46	android/os/Parcel:readException	()V
    //   59: aload 4
    //   61: invokevirtual 49	android/os/Parcel:recycle	()V
    //   64: aload_3
    //   65: invokevirtual 49	android/os/Parcel:recycle	()V
    //   68: return
    //   69: aconst_null
    //   70: astore 6
    //   72: goto -45 -> 27
    //   75: astore 5
    //   77: aload 4
    //   79: invokevirtual 49	android/os/Parcel:recycle	()V
    //   82: aload_3
    //   83: invokevirtual 49	android/os/Parcel:recycle	()V
    //   86: aload 5
    //   88: athrow
    // Local variable table:
    //   start	length	slot	name	signature
    //   0	89	0	this	fbt
    //   0	89	1	paramfbo	fbo
    //   0	89	2	paramString	java.lang.String
    //   3	80	3	localParcel1	android.os.Parcel
    //   7	71	4	localParcel2	android.os.Parcel
    //   75	12	5	localObject	Object
    //   25	46	6	localIBinder	IBinder
    // Exception table:
    //   from	to	target	type
    //   9	15	75	finally
    //   19	27	75	finally
    //   27	59	75	finally
  }
  
  /* Error */
  public final void e(fbo paramfbo)
  {
    // Byte code:
    //   0: invokestatic 22	android/os/Parcel:obtain	()Landroid/os/Parcel;
    //   3: astore_2
    //   4: invokestatic 22	android/os/Parcel:obtain	()Landroid/os/Parcel;
    //   7: astore_3
    //   8: aload_2
    //   9: ldc 24
    //   11: invokevirtual 28	android/os/Parcel:writeInterfaceToken	(Ljava/lang/String;)V
    //   14: aload_1
    //   15: ifnull +45 -> 60
    //   18: aload_1
    //   19: invokeinterface 34 1 0
    //   24: astore 5
    //   26: aload_2
    //   27: aload 5
    //   29: invokevirtual 37	android/os/Parcel:writeStrongBinder	(Landroid/os/IBinder;)V
    //   32: aload_0
    //   33: getfield 15	fbt:a	Landroid/os/IBinder;
    //   36: bipush 13
    //   38: aload_2
    //   39: aload_3
    //   40: iconst_0
    //   41: invokeinterface 43 5 0
    //   46: pop
    //   47: aload_3
    //   48: invokevirtual 46	android/os/Parcel:readException	()V
    //   51: aload_3
    //   52: invokevirtual 49	android/os/Parcel:recycle	()V
    //   55: aload_2
    //   56: invokevirtual 49	android/os/Parcel:recycle	()V
    //   59: return
    //   60: aconst_null
    //   61: astore 5
    //   63: goto -37 -> 26
    //   66: astore 4
    //   68: aload_3
    //   69: invokevirtual 49	android/os/Parcel:recycle	()V
    //   72: aload_2
    //   73: invokevirtual 49	android/os/Parcel:recycle	()V
    //   76: aload 4
    //   78: athrow
    // Local variable table:
    //   start	length	slot	name	signature
    //   0	79	0	this	fbt
    //   0	79	1	paramfbo	fbo
    //   3	70	2	localParcel1	android.os.Parcel
    //   7	62	3	localParcel2	android.os.Parcel
    //   66	11	4	localObject	Object
    //   24	38	5	localIBinder	IBinder
    // Exception table:
    //   from	to	target	type
    //   8	14	66	finally
    //   18	26	66	finally
    //   26	51	66	finally
  }
  
  /* Error */
  public final void e(fbo paramfbo, java.lang.String paramString)
  {
    // Byte code:
    //   0: invokestatic 22	android/os/Parcel:obtain	()Landroid/os/Parcel;
    //   3: astore_3
    //   4: invokestatic 22	android/os/Parcel:obtain	()Landroid/os/Parcel;
    //   7: astore 4
    //   9: aload_3
    //   10: ldc 24
    //   12: invokevirtual 28	android/os/Parcel:writeInterfaceToken	(Ljava/lang/String;)V
    //   15: aload_1
    //   16: ifnull +53 -> 69
    //   19: aload_1
    //   20: invokeinterface 34 1 0
    //   25: astore 6
    //   27: aload_3
    //   28: aload 6
    //   30: invokevirtual 37	android/os/Parcel:writeStrongBinder	(Landroid/os/IBinder;)V
    //   33: aload_3
    //   34: aload_2
    //   35: invokevirtual 64	android/os/Parcel:writeString	(Ljava/lang/String;)V
    //   38: aload_0
    //   39: getfield 15	fbt:a	Landroid/os/IBinder;
    //   42: bipush 11
    //   44: aload_3
    //   45: aload 4
    //   47: iconst_0
    //   48: invokeinterface 43 5 0
    //   53: pop
    //   54: aload 4
    //   56: invokevirtual 46	android/os/Parcel:readException	()V
    //   59: aload 4
    //   61: invokevirtual 49	android/os/Parcel:recycle	()V
    //   64: aload_3
    //   65: invokevirtual 49	android/os/Parcel:recycle	()V
    //   68: return
    //   69: aconst_null
    //   70: astore 6
    //   72: goto -45 -> 27
    //   75: astore 5
    //   77: aload 4
    //   79: invokevirtual 49	android/os/Parcel:recycle	()V
    //   82: aload_3
    //   83: invokevirtual 49	android/os/Parcel:recycle	()V
    //   86: aload 5
    //   88: athrow
    // Local variable table:
    //   start	length	slot	name	signature
    //   0	89	0	this	fbt
    //   0	89	1	paramfbo	fbo
    //   0	89	2	paramString	java.lang.String
    //   3	80	3	localParcel1	android.os.Parcel
    //   7	71	4	localParcel2	android.os.Parcel
    //   75	12	5	localObject	Object
    //   25	46	6	localIBinder	IBinder
    // Exception table:
    //   from	to	target	type
    //   9	15	75	finally
    //   19	27	75	finally
    //   27	59	75	finally
  }
}


/* Location:           F:\apktool\apktool\com.google.android.apps.plus\classes-dex2jar.jar
 * Qualified Name:     fbt
 * JD-Core Version:    0.7.0.1
 */