import android.os.IBinder;

public final class fec
  implements fea
{
  private IBinder a;
  
  public fec(IBinder paramIBinder)
  {
    this.a = paramIBinder;
  }
  
  /* Error */
  public final void a(com.google.android.gms.location.LocationAvailability paramLocationAvailability)
  {
    // Byte code:
    //   0: invokestatic 22	android/os/Parcel:obtain	()Landroid/os/Parcel;
    //   3: astore_2
    //   4: aload_2
    //   5: ldc 24
    //   7: invokevirtual 28	android/os/Parcel:writeInterfaceToken	(Ljava/lang/String;)V
    //   10: aload_1
    //   11: ifnull +33 -> 44
    //   14: aload_2
    //   15: iconst_1
    //   16: invokevirtual 32	android/os/Parcel:writeInt	(I)V
    //   19: aload_1
    //   20: aload_2
    //   21: iconst_0
    //   22: invokevirtual 38	com/google/android/gms/location/LocationAvailability:writeToParcel	(Landroid/os/Parcel;I)V
    //   25: aload_0
    //   26: getfield 15	fec:a	Landroid/os/IBinder;
    //   29: iconst_2
    //   30: aload_2
    //   31: aconst_null
    //   32: iconst_1
    //   33: invokeinterface 44 5 0
    //   38: pop
    //   39: aload_2
    //   40: invokevirtual 47	android/os/Parcel:recycle	()V
    //   43: return
    //   44: aload_2
    //   45: iconst_0
    //   46: invokevirtual 32	android/os/Parcel:writeInt	(I)V
    //   49: goto -24 -> 25
    //   52: astore_3
    //   53: aload_2
    //   54: invokevirtual 47	android/os/Parcel:recycle	()V
    //   57: aload_3
    //   58: athrow
    // Local variable table:
    //   start	length	slot	name	signature
    //   0	59	0	this	fec
    //   0	59	1	paramLocationAvailability	com.google.android.gms.location.LocationAvailability
    //   3	51	2	localParcel	android.os.Parcel
    //   52	6	3	localObject	Object
    // Exception table:
    //   from	to	target	type
    //   4	10	52	finally
    //   14	25	52	finally
    //   25	39	52	finally
    //   44	49	52	finally
  }
  
  /* Error */
  public final void a(com.google.android.gms.location.LocationResult paramLocationResult)
  {
    // Byte code:
    //   0: invokestatic 22	android/os/Parcel:obtain	()Landroid/os/Parcel;
    //   3: astore_2
    //   4: aload_2
    //   5: ldc 24
    //   7: invokevirtual 28	android/os/Parcel:writeInterfaceToken	(Ljava/lang/String;)V
    //   10: aload_1
    //   11: ifnull +33 -> 44
    //   14: aload_2
    //   15: iconst_1
    //   16: invokevirtual 32	android/os/Parcel:writeInt	(I)V
    //   19: aload_1
    //   20: aload_2
    //   21: iconst_0
    //   22: invokevirtual 51	com/google/android/gms/location/LocationResult:writeToParcel	(Landroid/os/Parcel;I)V
    //   25: aload_0
    //   26: getfield 15	fec:a	Landroid/os/IBinder;
    //   29: iconst_1
    //   30: aload_2
    //   31: aconst_null
    //   32: iconst_1
    //   33: invokeinterface 44 5 0
    //   38: pop
    //   39: aload_2
    //   40: invokevirtual 47	android/os/Parcel:recycle	()V
    //   43: return
    //   44: aload_2
    //   45: iconst_0
    //   46: invokevirtual 32	android/os/Parcel:writeInt	(I)V
    //   49: goto -24 -> 25
    //   52: astore_3
    //   53: aload_2
    //   54: invokevirtual 47	android/os/Parcel:recycle	()V
    //   57: aload_3
    //   58: athrow
    // Local variable table:
    //   start	length	slot	name	signature
    //   0	59	0	this	fec
    //   0	59	1	paramLocationResult	com.google.android.gms.location.LocationResult
    //   3	51	2	localParcel	android.os.Parcel
    //   52	6	3	localObject	Object
    // Exception table:
    //   from	to	target	type
    //   4	10	52	finally
    //   14	25	52	finally
    //   25	39	52	finally
    //   44	49	52	finally
  }
  
  public final IBinder asBinder()
  {
    return this.a;
  }
}


/* Location:           F:\apktool\apktool\com.google.android.apps.plus\classes-dex2jar.jar
 * Qualified Name:     fec
 * JD-Core Version:    0.7.0.1
 */