final class gzv
  implements Runnable
{
  gzv(gzs paramgzs, gzf paramgzf) {}
  
  /* Error */
  public final void run()
  {
    // Byte code:
    //   0: aload_0
    //   1: getfield 16	gzv:a	Lgzf;
    //   4: astore_1
    //   5: aload_0
    //   6: getfield 14	gzv:b	Lgzs;
    //   9: getfield 27	gzs:a	Landroid/content/Context;
    //   12: astore_2
    //   13: new 29	hae
    //   16: dup
    //   17: iconst_0
    //   18: invokespecial 32	hae:<init>	(Z)V
    //   21: astore_3
    //   22: aload_1
    //   23: aload_2
    //   24: invokevirtual 38	gzf:e	(Landroid/content/Context;)Lhae;
    //   27: astore 9
    //   29: aload_1
    //   30: getfield 42	gzf:g	Lgzg;
    //   33: aload_1
    //   34: aload 9
    //   36: invokeinterface 47 3 0
    //   41: aload_1
    //   42: aload_2
    //   43: invokevirtual 51	gzf:d	(Landroid/content/Context;)V
    //   46: return
    //   47: astore 10
    //   49: aload_1
    //   50: aload_2
    //   51: invokevirtual 51	gzf:d	(Landroid/content/Context;)V
    //   54: aload 10
    //   56: athrow
    //   57: astore 6
    //   59: invokestatic 57	java/lang/Thread:getDefaultUncaughtExceptionHandler	()Ljava/lang/Thread$UncaughtExceptionHandler;
    //   62: astore 7
    //   64: aload 7
    //   66: ifnull +32 -> 98
    //   69: aload 7
    //   71: invokestatic 61	java/lang/Thread:currentThread	()Ljava/lang/Thread;
    //   74: aload 6
    //   76: invokeinterface 67 3 0
    //   81: aload_1
    //   82: getfield 42	gzf:g	Lgzg;
    //   85: aload_1
    //   86: aload_3
    //   87: invokeinterface 47 3 0
    //   92: aload_1
    //   93: aload_2
    //   94: invokevirtual 51	gzf:d	(Landroid/content/Context;)V
    //   97: return
    //   98: new 69	java/lang/RuntimeException
    //   101: dup
    //   102: aload 6
    //   104: invokespecial 72	java/lang/RuntimeException:<init>	(Ljava/lang/Throwable;)V
    //   107: athrow
    //   108: astore 4
    //   110: aload_1
    //   111: getfield 42	gzf:g	Lgzg;
    //   114: aload_1
    //   115: aload_3
    //   116: invokeinterface 47 3 0
    //   121: aload_1
    //   122: aload_2
    //   123: invokevirtual 51	gzf:d	(Landroid/content/Context;)V
    //   126: aload 4
    //   128: athrow
    //   129: astore 8
    //   131: aload_1
    //   132: aload_2
    //   133: invokevirtual 51	gzf:d	(Landroid/content/Context;)V
    //   136: aload 8
    //   138: athrow
    //   139: astore 5
    //   141: aload_1
    //   142: aload_2
    //   143: invokevirtual 51	gzf:d	(Landroid/content/Context;)V
    //   146: aload 5
    //   148: athrow
    // Local variable table:
    //   start	length	slot	name	signature
    //   0	149	0	this	gzv
    //   4	138	1	localgzf	gzf
    //   12	131	2	localContext	android.content.Context
    //   21	95	3	localhae1	hae
    //   108	19	4	localObject1	Object
    //   139	8	5	localObject2	Object
    //   57	46	6	localThrowable	java.lang.Throwable
    //   62	8	7	localUncaughtExceptionHandler	java.lang.Thread.UncaughtExceptionHandler
    //   129	8	8	localObject3	Object
    //   27	8	9	localhae2	hae
    //   47	8	10	localObject4	Object
    // Exception table:
    //   from	to	target	type
    //   29	41	47	finally
    //   22	29	57	java/lang/Throwable
    //   22	29	108	finally
    //   59	64	108	finally
    //   69	81	108	finally
    //   98	108	108	finally
    //   81	92	129	finally
    //   110	121	139	finally
  }
}


/* Location:           F:\apktool\apktool\com.google.android.apps.plus\classes-dex2jar.jar
 * Qualified Name:     gzv
 * JD-Core Version:    0.7.0.1
 */