import org.chromium.net.HttpUrlRequest;
import org.chromium.net.HttpUrlRequestListener;

final class hvx
  implements HttpUrlRequestListener
{
  hvx(hvu paramhvu) {}
  
  public final void a(HttpUrlRequest paramHttpUrlRequest) {}
  
  /* Error */
  public final void b(HttpUrlRequest paramHttpUrlRequest)
  {
    // Byte code:
    //   0: aload_1
    //   1: invokeinterface 23 1 0
    //   6: ifnonnull +243 -> 249
    //   9: aload_0
    //   10: getfield 12	hvx:a	Lhvu;
    //   13: getfield 28	hvu:b	Landroid/content/SharedPreferences;
    //   16: invokeinterface 34 1 0
    //   21: astore 7
    //   23: new 36	java/lang/String
    //   26: dup
    //   27: aload_1
    //   28: invokeinterface 40 1 0
    //   33: ldc 42
    //   35: invokestatic 48	java/nio/charset/Charset:forName	(Ljava/lang/String;)Ljava/nio/charset/Charset;
    //   38: invokespecial 51	java/lang/String:<init>	([BLjava/nio/charset/Charset;)V
    //   41: ldc 53
    //   43: invokevirtual 57	java/lang/String:split	(Ljava/lang/String;)[Ljava/lang/String;
    //   46: astore 8
    //   48: aload 7
    //   50: ldc 59
    //   52: ldc 61
    //   54: invokeinterface 67 3 0
    //   59: pop
    //   60: ldc 69
    //   62: iconst_2
    //   63: invokestatic 75	android/util/Log:isLoggable	(Ljava/lang/String;I)Z
    //   66: ifeq +29 -> 95
    //   69: aload 8
    //   71: invokestatic 81	java/util/Arrays:toString	([Ljava/lang/Object;)Ljava/lang/String;
    //   74: invokestatic 85	java/lang/String:valueOf	(Ljava/lang/Object;)Ljava/lang/String;
    //   77: astore 14
    //   79: aload 14
    //   81: invokevirtual 89	java/lang/String:length	()I
    //   84: ifeq +106 -> 190
    //   87: ldc 91
    //   89: aload 14
    //   91: invokevirtual 95	java/lang/String:concat	(Ljava/lang/String;)Ljava/lang/String;
    //   94: pop
    //   95: new 97	kl
    //   98: dup
    //   99: aload 8
    //   101: arraylength
    //   102: iconst_2
    //   103: idiv
    //   104: invokespecial 100	kl:<init>	(I)V
    //   107: astore 10
    //   109: iconst_1
    //   110: istore 11
    //   112: iload 11
    //   114: aload 8
    //   116: arraylength
    //   117: if_icmpge +106 -> 223
    //   120: aload 10
    //   122: aload 8
    //   124: iload 11
    //   126: aaload
    //   127: aload 8
    //   129: iload 11
    //   131: iconst_1
    //   132: iadd
    //   133: aaload
    //   134: invokeinterface 106 3 0
    //   139: pop
    //   140: aload 8
    //   142: iload 11
    //   144: iconst_1
    //   145: iadd
    //   146: aaload
    //   147: aload_0
    //   148: getfield 12	hvx:a	Lhvu;
    //   151: getfield 28	hvu:b	Landroid/content/SharedPreferences;
    //   154: aload 8
    //   156: iload 11
    //   158: aaload
    //   159: ldc 108
    //   161: invokeinterface 112 3 0
    //   166: invokevirtual 116	java/lang/String:equals	(Ljava/lang/Object;)Z
    //   169: ifne +116 -> 285
    //   172: aload 7
    //   174: aload 8
    //   176: iload 11
    //   178: aaload
    //   179: ldc 118
    //   181: invokeinterface 67 3 0
    //   186: pop
    //   187: goto +98 -> 285
    //   190: new 36	java/lang/String
    //   193: dup
    //   194: ldc 91
    //   196: invokespecial 121	java/lang/String:<init>	(Ljava/lang/String;)V
    //   199: pop
    //   200: goto -105 -> 95
    //   203: astore_2
    //   204: aload_0
    //   205: getfield 12	hvx:a	Lhvu;
    //   208: astore_3
    //   209: aload_3
    //   210: monitorenter
    //   211: aload_0
    //   212: getfield 12	hvx:a	Lhvu;
    //   215: iconst_0
    //   216: putfield 124	hvu:c	Z
    //   219: aload_3
    //   220: monitorexit
    //   221: aload_2
    //   222: athrow
    //   223: aload 10
    //   225: invokeinterface 128 1 0
    //   230: ifne +19 -> 249
    //   233: aload 7
    //   235: invokeinterface 131 1 0
    //   240: aload_0
    //   241: getfield 12	hvx:a	Lhvu;
    //   244: aload 10
    //   246: invokestatic 134	hvu:a	(Lhvu;Ljava/util/Map;)V
    //   249: aload_0
    //   250: getfield 12	hvx:a	Lhvu;
    //   253: astore 5
    //   255: aload 5
    //   257: monitorenter
    //   258: aload_0
    //   259: getfield 12	hvx:a	Lhvu;
    //   262: iconst_0
    //   263: putfield 124	hvu:c	Z
    //   266: aload 5
    //   268: monitorexit
    //   269: return
    //   270: astore 6
    //   272: aload 5
    //   274: monitorexit
    //   275: aload 6
    //   277: athrow
    //   278: astore 4
    //   280: aload_3
    //   281: monitorexit
    //   282: aload 4
    //   284: athrow
    //   285: iinc 11 2
    //   288: goto -176 -> 112
    // Local variable table:
    //   start	length	slot	name	signature
    //   0	291	0	this	hvx
    //   0	291	1	paramHttpUrlRequest	HttpUrlRequest
    //   203	19	2	localObject1	Object
    //   208	73	3	localhvu1	hvu
    //   278	5	4	localObject2	Object
    //   270	6	6	localObject3	Object
    //   21	213	7	localEditor	android.content.SharedPreferences.Editor
    //   46	129	8	arrayOfString	java.lang.String[]
    //   107	138	10	localkl	kl
    //   110	176	11	i	int
    //   77	13	14	str	java.lang.String
    // Exception table:
    //   from	to	target	type
    //   0	95	203	finally
    //   95	109	203	finally
    //   112	187	203	finally
    //   190	200	203	finally
    //   223	249	203	finally
    //   258	269	270	finally
    //   272	275	270	finally
    //   211	221	278	finally
    //   280	282	278	finally
  }
}


/* Location:           F:\apktool\apktool\com.google.android.apps.plus\classes-dex2jar.jar
 * Qualified Name:     hvx
 * JD-Core Version:    0.7.0.1
 */