import java.util.HashMap;

final class jti
{
  HashMap<String, Integer> a = new HashMap();
  private String b;
  
  public jti(String paramString)
  {
    this.b = paramString;
    b();
  }
  
  /* Error */
  private final void b()
  {
    // Byte code:
    //   0: new 27	java/io/File
    //   3: dup
    //   4: aload_0
    //   5: getfield 21	jti:b	Ljava/lang/String;
    //   8: invokespecial 29	java/io/File:<init>	(Ljava/lang/String;)V
    //   11: astore_1
    //   12: aload_1
    //   13: invokevirtual 33	java/io/File:exists	()Z
    //   16: ifne +4 -> 20
    //   19: return
    //   20: new 35	java/io/BufferedReader
    //   23: dup
    //   24: new 37	java/io/FileReader
    //   27: dup
    //   28: aload_1
    //   29: invokespecial 40	java/io/FileReader:<init>	(Ljava/io/File;)V
    //   32: invokespecial 43	java/io/BufferedReader:<init>	(Ljava/io/Reader;)V
    //   35: astore_2
    //   36: aload_2
    //   37: invokevirtual 47	java/io/BufferedReader:readLine	()Ljava/lang/String;
    //   40: astore 5
    //   42: aload 5
    //   44: ifnull +127 -> 171
    //   47: aload 5
    //   49: bipush 61
    //   51: invokevirtual 53	java/lang/String:lastIndexOf	(I)I
    //   54: istore 6
    //   56: iload 6
    //   58: iconst_m1
    //   59: if_icmpeq +52 -> 111
    //   62: aload 5
    //   64: iconst_0
    //   65: iload 6
    //   67: invokevirtual 57	java/lang/String:substring	(II)Ljava/lang/String;
    //   70: invokevirtual 60	java/lang/String:trim	()Ljava/lang/String;
    //   73: astore 7
    //   75: aload 5
    //   77: iload 6
    //   79: iconst_1
    //   80: iadd
    //   81: invokevirtual 63	java/lang/String:substring	(I)Ljava/lang/String;
    //   84: invokevirtual 60	java/lang/String:trim	()Ljava/lang/String;
    //   87: astore 8
    //   89: aload 8
    //   91: invokestatic 69	java/lang/Integer:parseInt	(Ljava/lang/String;)I
    //   94: istore 13
    //   96: aload_0
    //   97: getfield 19	jti:a	Ljava/util/HashMap;
    //   100: aload 7
    //   102: iload 13
    //   104: invokestatic 73	java/lang/Integer:valueOf	(I)Ljava/lang/Integer;
    //   107: invokevirtual 77	java/util/HashMap:put	(Ljava/lang/Object;Ljava/lang/Object;)Ljava/lang/Object;
    //   110: pop
    //   111: aload_2
    //   112: invokevirtual 47	java/io/BufferedReader:readLine	()Ljava/lang/String;
    //   115: astore 5
    //   117: goto -75 -> 42
    //   120: astore 9
    //   122: aload 5
    //   124: invokestatic 80	java/lang/String:valueOf	(Ljava/lang/Object;)Ljava/lang/String;
    //   127: astore 10
    //   129: aload 10
    //   131: invokevirtual 84	java/lang/String:length	()I
    //   134: ifeq +24 -> 158
    //   137: ldc 86
    //   139: aload 10
    //   141: invokevirtual 90	java/lang/String:concat	(Ljava/lang/String;)Ljava/lang/String;
    //   144: pop
    //   145: goto -34 -> 111
    //   148: astore_3
    //   149: aload_2
    //   150: invokestatic 95	iaw:a	(Ljava/io/Closeable;)V
    //   153: aload_3
    //   154: athrow
    //   155: astore 4
    //   157: return
    //   158: new 49	java/lang/String
    //   161: dup
    //   162: ldc 86
    //   164: invokespecial 96	java/lang/String:<init>	(Ljava/lang/String;)V
    //   167: pop
    //   168: goto -57 -> 111
    //   171: aload_2
    //   172: invokestatic 95	iaw:a	(Ljava/io/Closeable;)V
    //   175: return
    // Local variable table:
    //   start	length	slot	name	signature
    //   0	176	0	this	jti
    //   11	18	1	localFile	java.io.File
    //   35	137	2	localBufferedReader	java.io.BufferedReader
    //   148	6	3	localObject	Object
    //   155	1	4	localThrowable1	java.lang.Throwable
    //   40	83	5	str1	String
    //   54	27	6	i	int
    //   73	28	7	str2	String
    //   87	3	8	str3	String
    //   120	1	9	localThrowable2	java.lang.Throwable
    //   127	13	10	str4	String
    //   94	9	13	j	int
    // Exception table:
    //   from	to	target	type
    //   89	111	120	java/lang/Throwable
    //   36	42	148	finally
    //   47	56	148	finally
    //   62	89	148	finally
    //   89	111	148	finally
    //   111	117	148	finally
    //   122	145	148	finally
    //   158	168	148	finally
    //   20	36	155	java/lang/Throwable
    //   149	155	155	java/lang/Throwable
    //   171	175	155	java/lang/Throwable
  }
  
  /* Error */
  public final void a()
  {
    // Byte code:
    //   0: new 98	java/io/PrintWriter
    //   3: dup
    //   4: new 27	java/io/File
    //   7: dup
    //   8: aload_0
    //   9: getfield 21	jti:b	Ljava/lang/String;
    //   12: invokespecial 29	java/io/File:<init>	(Ljava/lang/String;)V
    //   15: invokespecial 99	java/io/PrintWriter:<init>	(Ljava/io/File;)V
    //   18: astore_1
    //   19: aload_0
    //   20: getfield 19	jti:a	Ljava/util/HashMap;
    //   23: invokevirtual 103	java/util/HashMap:entrySet	()Ljava/util/Set;
    //   26: invokeinterface 109 1 0
    //   31: astore 5
    //   33: aload 5
    //   35: invokeinterface 114 1 0
    //   40: ifeq +69 -> 109
    //   43: aload 5
    //   45: invokeinterface 118 1 0
    //   50: checkcast 120	java/util/Map$Entry
    //   53: astore 6
    //   55: iconst_2
    //   56: anewarray 4	java/lang/Object
    //   59: astore 7
    //   61: aload 7
    //   63: iconst_0
    //   64: aload 6
    //   66: invokeinterface 123 1 0
    //   71: aastore
    //   72: aload 7
    //   74: iconst_1
    //   75: aload 6
    //   77: invokeinterface 126 1 0
    //   82: aastore
    //   83: aload_1
    //   84: ldc 128
    //   86: aload 7
    //   88: invokevirtual 132	java/io/PrintWriter:printf	(Ljava/lang/String;[Ljava/lang/Object;)Ljava/io/PrintWriter;
    //   91: pop
    //   92: aload_1
    //   93: invokevirtual 135	java/io/PrintWriter:println	()V
    //   96: goto -63 -> 33
    //   99: astore_3
    //   100: aload_1
    //   101: astore 4
    //   103: aload 4
    //   105: invokestatic 95	iaw:a	(Ljava/io/Closeable;)V
    //   108: return
    //   109: aload_1
    //   110: invokestatic 95	iaw:a	(Ljava/io/Closeable;)V
    //   113: return
    //   114: astore 10
    //   116: aconst_null
    //   117: astore_1
    //   118: aload 10
    //   120: astore_2
    //   121: aload_1
    //   122: invokestatic 95	iaw:a	(Ljava/io/Closeable;)V
    //   125: aload_2
    //   126: athrow
    //   127: astore_2
    //   128: goto -7 -> 121
    //   131: astore 9
    //   133: aconst_null
    //   134: astore 4
    //   136: goto -33 -> 103
    // Local variable table:
    //   start	length	slot	name	signature
    //   0	139	0	this	jti
    //   18	104	1	localPrintWriter1	java.io.PrintWriter
    //   120	6	2	localObject1	Object
    //   127	1	2	localObject2	Object
    //   99	1	3	localThrowable1	java.lang.Throwable
    //   101	34	4	localPrintWriter2	java.io.PrintWriter
    //   31	13	5	localIterator	java.util.Iterator
    //   53	23	6	localEntry	java.util.Map.Entry
    //   59	28	7	arrayOfObject	Object[]
    //   131	1	9	localThrowable2	java.lang.Throwable
    //   114	5	10	localObject3	Object
    // Exception table:
    //   from	to	target	type
    //   19	33	99	java/lang/Throwable
    //   33	96	99	java/lang/Throwable
    //   0	19	114	finally
    //   19	33	127	finally
    //   33	96	127	finally
    //   0	19	131	java/lang/Throwable
  }
}


/* Location:           F:\apktool\apktool\com.google.android.apps.plus\classes-dex2jar.jar
 * Qualified Name:     jti
 * JD-Core Version:    0.7.0.1
 */