final class ljn
  implements ovz<Boolean>
{
  ljn(ljm paramljm) {}
  
  /* Error */
  private Boolean b(owa paramowa)
  {
    // Byte code:
    //   0: new 20	oxk
    //   3: dup
    //   4: invokespecial 21	oxk:<init>	()V
    //   7: astore_2
    //   8: aload_2
    //   9: getfield 24	oxk:a	Ljava/lang/StringBuilder;
    //   12: ldc 26
    //   14: invokevirtual 32	java/lang/StringBuilder:append	(Ljava/lang/String;)Ljava/lang/StringBuilder;
    //   17: pop
    //   18: aload_0
    //   19: getfield 13	ljn:a	Lljm;
    //   22: getfield 37	ljm:a	Lqzz;
    //   25: getfield 43	qzz:c	Ljava/lang/String;
    //   28: invokestatic 49	java/lang/String:valueOf	(Ljava/lang/Object;)Ljava/lang/String;
    //   31: astore 4
    //   33: aload_2
    //   34: getfield 52	oxk:b	Ljava/util/ArrayList;
    //   37: aload 4
    //   39: invokevirtual 58	java/util/ArrayList:add	(Ljava/lang/Object;)Z
    //   42: pop
    //   43: aload_1
    //   44: aload_2
    //   45: invokevirtual 61	oxk:a	()Loxl;
    //   48: invokevirtual 66	owa:a	(Loxl;)Landroid/database/Cursor;
    //   51: astore 6
    //   53: aload 6
    //   55: invokeinterface 72 1 0
    //   60: ifne +19 -> 79
    //   63: iconst_0
    //   64: invokestatic 77	java/lang/Boolean:valueOf	(Z)Ljava/lang/Boolean;
    //   67: astore 17
    //   69: aload 6
    //   71: invokeinterface 80 1 0
    //   76: aload 17
    //   78: areturn
    //   79: aload 6
    //   81: invokeinterface 80 1 0
    //   86: new 82	android/content/ContentValues
    //   89: dup
    //   90: invokespecial 83	android/content/ContentValues:<init>	()V
    //   93: astore 8
    //   95: aload_0
    //   96: getfield 13	ljn:a	Lljm;
    //   99: getfield 87	ljm:d	Lljg;
    //   102: getfield 92	ljg:b	Lhgs;
    //   105: invokeinterface 97 1 0
    //   110: lstore 9
    //   112: new 20	oxk
    //   115: dup
    //   116: invokespecial 21	oxk:<init>	()V
    //   119: astore 11
    //   121: aload 11
    //   123: getfield 24	oxk:a	Ljava/lang/StringBuilder;
    //   126: ldc 99
    //   128: invokevirtual 32	java/lang/StringBuilder:append	(Ljava/lang/String;)Ljava/lang/StringBuilder;
    //   131: pop
    //   132: aload_1
    //   133: aload 11
    //   135: invokevirtual 61	oxk:a	()Loxl;
    //   138: invokevirtual 66	owa:a	(Loxl;)Landroid/database/Cursor;
    //   141: astore 13
    //   143: aload 13
    //   145: invokeinterface 103 1 0
    //   150: pop
    //   151: aload 13
    //   153: aload 13
    //   155: ldc 105
    //   157: invokeinterface 109 2 0
    //   162: invokeinterface 113 2 0
    //   167: istore 16
    //   169: aload 13
    //   171: invokeinterface 80 1 0
    //   176: aload_0
    //   177: getfield 13	ljn:a	Lljm;
    //   180: getfield 87	ljm:d	Lljg;
    //   183: iload 16
    //   185: aload_1
    //   186: lload 9
    //   188: aload_0
    //   189: getfield 13	ljn:a	Lljm;
    //   192: getfield 116	ljm:b	Ljava/util/List;
    //   195: aload_0
    //   196: getfield 13	ljn:a	Lljm;
    //   199: getfield 118	ljm:c	Ljava/util/List;
    //   202: aload 8
    //   204: invokestatic 121	ljg:a	(Lljg;ILowa;JLjava/util/List;Ljava/util/List;Landroid/content/ContentValues;)V
    //   207: iconst_1
    //   208: invokestatic 77	java/lang/Boolean:valueOf	(Z)Ljava/lang/Boolean;
    //   211: areturn
    //   212: astore 7
    //   214: aload 6
    //   216: invokeinterface 80 1 0
    //   221: aload 7
    //   223: athrow
    //   224: astore 14
    //   226: aload 13
    //   228: invokeinterface 80 1 0
    //   233: aload 14
    //   235: athrow
    // Local variable table:
    //   start	length	slot	name	signature
    //   0	236	0	this	ljn
    //   0	236	1	paramowa	owa
    //   7	38	2	localoxk1	oxk
    //   31	7	4	str	java.lang.String
    //   51	164	6	localCursor1	android.database.Cursor
    //   212	10	7	localObject1	Object
    //   93	110	8	localContentValues	android.content.ContentValues
    //   110	77	9	l	long
    //   119	15	11	localoxk2	oxk
    //   141	86	13	localCursor2	android.database.Cursor
    //   224	10	14	localObject2	Object
    //   167	17	16	i	int
    //   67	10	17	localBoolean	Boolean
    // Exception table:
    //   from	to	target	type
    //   53	69	212	finally
    //   143	169	224	finally
  }
}


/* Location:           F:\apktool\apktool\com.google.android.apps.plus\classes-dex2jar.jar
 * Qualified Name:     ljn
 * JD-Core Version:    0.7.0.1
 */