final class ljz
  implements ovz<kx>
{
  ljz(ljy paramljy) {}
  
  /* Error */
  private kx b(owa paramowa)
  {
    // Byte code:
    //   0: new 20	kl
    //   3: dup
    //   4: invokespecial 21	kl:<init>	()V
    //   7: astore_2
    //   8: new 23	java/util/ArrayList
    //   11: dup
    //   12: invokespecial 24	java/util/ArrayList:<init>	()V
    //   15: astore_3
    //   16: new 26	oxk
    //   19: dup
    //   20: invokespecial 27	oxk:<init>	()V
    //   23: astore 4
    //   25: aload 4
    //   27: getfield 30	oxk:a	Ljava/lang/StringBuilder;
    //   30: ldc 32
    //   32: invokevirtual 38	java/lang/StringBuilder:append	(Ljava/lang/String;)Ljava/lang/StringBuilder;
    //   35: pop
    //   36: aload_0
    //   37: getfield 13	ljz:a	Lljy;
    //   40: getfield 43	ljy:a	Ljava/lang/String;
    //   43: invokestatic 49	java/lang/String:valueOf	(Ljava/lang/Object;)Ljava/lang/String;
    //   46: astore 6
    //   48: aload 4
    //   50: getfield 52	oxk:b	Ljava/util/ArrayList;
    //   53: aload 6
    //   55: invokevirtual 56	java/util/ArrayList:add	(Ljava/lang/Object;)Z
    //   58: pop
    //   59: aload_1
    //   60: aload 4
    //   62: invokevirtual 59	oxk:a	()Loxl;
    //   65: invokevirtual 64	owa:a	(Loxl;)Landroid/database/Cursor;
    //   68: astore 8
    //   70: aload 8
    //   72: invokeinterface 70 1 0
    //   77: istore 10
    //   79: iload 10
    //   81: ifne +12 -> 93
    //   84: aload 8
    //   86: invokeinterface 73 1 0
    //   91: aconst_null
    //   92: areturn
    //   93: aload 8
    //   95: invokeinterface 77 1 0
    //   100: pop
    //   101: aload 8
    //   103: aload 8
    //   105: ldc 79
    //   107: invokeinterface 83 2 0
    //   112: invokeinterface 87 2 0
    //   117: astore 12
    //   119: aload_0
    //   120: getfield 13	ljz:a	Lljy;
    //   123: getfield 90	ljy:b	Lljg;
    //   126: getfield 96	ljg:c	Lpxz;
    //   129: astore 13
    //   131: getstatic 102	qzz:d	Lqzz;
    //   134: getstatic 108	pym:h	I
    //   137: aconst_null
    //   138: aconst_null
    //   139: invokevirtual 113	pye:a	(ILjava/lang/Object;Ljava/lang/Object;)Ljava/lang/Object;
    //   142: checkcast 115	pzh
    //   145: aload 12
    //   147: aload 13
    //   149: invokeinterface 118 3 0
    //   154: checkcast 98	qzz
    //   157: astore 14
    //   159: aload_3
    //   160: aload_0
    //   161: getfield 13	ljz:a	Lljy;
    //   164: getfield 43	ljy:a	Ljava/lang/String;
    //   167: invokevirtual 56	java/util/ArrayList:add	(Ljava/lang/Object;)Z
    //   170: pop
    //   171: aload 8
    //   173: invokeinterface 73 1 0
    //   178: ldc 120
    //   180: invokestatic 125	pea:a	(Ljava/lang/String;)Lpdc;
    //   183: astore 16
    //   185: aload_3
    //   186: invokevirtual 128	java/util/ArrayList:isEmpty	()Z
    //   189: ifne +36 -> 225
    //   192: aload_0
    //   193: getfield 13	ljz:a	Lljy;
    //   196: getfield 90	ljy:b	Lljg;
    //   199: aload_1
    //   200: aload_3
    //   201: aload_2
    //   202: invokevirtual 131	ljg:a	(Lowa;Ljava/util/ArrayList;Lkl;)Ljava/util/ArrayList;
    //   205: astore 18
    //   207: aload 18
    //   209: astore_3
    //   210: goto -25 -> 185
    //   213: astore 9
    //   215: aload 8
    //   217: invokeinterface 73 1 0
    //   222: aload 9
    //   224: athrow
    //   225: aload 16
    //   227: invokevirtual 134	pdc:close	()V
    //   230: ldc 120
    //   232: invokestatic 137	pea:b	(Ljava/lang/String;)V
    //   235: new 139	kx
    //   238: dup
    //   239: aload 14
    //   241: aload_2
    //   242: invokespecial 142	kx:<init>	(Lqzz;Ljava/util/Map;)V
    //   245: areturn
    //   246: astore 17
    //   248: aload 16
    //   250: invokevirtual 134	pdc:close	()V
    //   253: ldc 120
    //   255: invokestatic 137	pea:b	(Ljava/lang/String;)V
    //   258: aload 17
    //   260: athrow
    // Local variable table:
    //   start	length	slot	name	signature
    //   0	261	0	this	ljz
    //   0	261	1	paramowa	owa
    //   7	235	2	localkl	kl
    //   15	195	3	localObject1	Object
    //   23	38	4	localoxk	oxk
    //   46	8	6	str	java.lang.String
    //   68	148	8	localCursor	android.database.Cursor
    //   213	10	9	localObject2	Object
    //   77	3	10	i	int
    //   117	29	12	arrayOfByte	byte[]
    //   129	19	13	localpxz	pxz
    //   157	83	14	localqzz	qzz
    //   183	66	16	localpdc	pdc
    //   246	13	17	localObject3	Object
    //   205	3	18	localArrayList	java.util.ArrayList
    // Exception table:
    //   from	to	target	type
    //   70	79	213	finally
    //   93	171	213	finally
    //   185	207	246	finally
  }
}


/* Location:           F:\apktool\apktool\com.google.android.apps.plus\classes-dex2jar.jar
 * Qualified Name:     ljz
 * JD-Core Version:    0.7.0.1
 */