final class lsm
{
  boolean a;
  lsl b;
  private boolean c;
  private int d;
  private boolean e;
  private boolean f;
  
  /* Error */
  public final void a(javax.microedition.khronos.opengles.GL10 paramGL10)
  {
    // Byte code:
    //   0: iconst_1
    //   1: istore_2
    //   2: aload_0
    //   3: monitorenter
    //   4: aload_0
    //   5: getfield 20	lsm:e	Z
    //   8: ifne +67 -> 75
    //   11: aload_0
    //   12: invokevirtual 22	lsm:c	()V
    //   15: aload_1
    //   16: sipush 7937
    //   19: invokeinterface 28 2 0
    //   24: astore 4
    //   26: aload_0
    //   27: getfield 30	lsm:d	I
    //   30: ldc 31
    //   32: if_icmpge +26 -> 58
    //   35: aload 4
    //   37: ldc 33
    //   39: invokevirtual 39	java/lang/String:startsWith	(Ljava/lang/String;)Z
    //   42: ifne +36 -> 78
    //   45: iload_2
    //   46: istore 5
    //   48: aload_0
    //   49: iload 5
    //   51: putfield 41	lsm:a	Z
    //   54: aload_0
    //   55: invokevirtual 44	java/lang/Object:notifyAll	()V
    //   58: aload_0
    //   59: getfield 41	lsm:a	Z
    //   62: ifne +22 -> 84
    //   65: aload_0
    //   66: iload_2
    //   67: putfield 46	lsm:f	Z
    //   70: aload_0
    //   71: iconst_1
    //   72: putfield 20	lsm:e	Z
    //   75: aload_0
    //   76: monitorexit
    //   77: return
    //   78: iconst_0
    //   79: istore 5
    //   81: goto -33 -> 48
    //   84: iconst_0
    //   85: istore_2
    //   86: goto -21 -> 65
    //   89: astore_3
    //   90: aload_0
    //   91: monitorexit
    //   92: aload_3
    //   93: athrow
    // Local variable table:
    //   start	length	slot	name	signature
    //   0	94	0	this	lsm
    //   0	94	1	paramGL10	javax.microedition.khronos.opengles.GL10
    //   1	85	2	bool1	boolean
    //   89	4	3	localObject	Object
    //   24	12	4	str	java.lang.String
    //   46	34	5	bool2	boolean
    // Exception table:
    //   from	to	target	type
    //   4	45	89	finally
    //   48	58	89	finally
    //   58	65	89	finally
    //   65	75	89	finally
  }
  
  public final void a(lsl paramlsl)
  {
    try
    {
      paramlsl.a = true;
      if (this.b == paramlsl) {
        this.b = null;
      }
      notifyAll();
      return;
    }
    finally {}
  }
  
  public final boolean a()
  {
    try
    {
      boolean bool = this.f;
      return bool;
    }
    finally
    {
      localObject = finally;
      throw localObject;
    }
  }
  
  public final void b(lsl paramlsl)
  {
    if (this.b == paramlsl) {
      this.b = null;
    }
    notifyAll();
  }
  
  /* Error */
  public final boolean b()
  {
    // Byte code:
    //   0: aload_0
    //   1: monitorenter
    //   2: aload_0
    //   3: invokevirtual 22	lsm:c	()V
    //   6: aload_0
    //   7: getfield 41	lsm:a	Z
    //   10: istore_2
    //   11: iload_2
    //   12: ifne +9 -> 21
    //   15: iconst_1
    //   16: istore_3
    //   17: aload_0
    //   18: monitorexit
    //   19: iload_3
    //   20: ireturn
    //   21: iconst_0
    //   22: istore_3
    //   23: goto -6 -> 17
    //   26: astore_1
    //   27: aload_0
    //   28: monitorexit
    //   29: aload_1
    //   30: athrow
    // Local variable table:
    //   start	length	slot	name	signature
    //   0	31	0	this	lsm
    //   26	4	1	localObject	Object
    //   10	2	2	bool1	boolean
    //   16	7	3	bool2	boolean
    // Exception table:
    //   from	to	target	type
    //   2	11	26	finally
  }
  
  final void c()
  {
    if (!this.c)
    {
      this.d = mga.a("ro.opengles.version", 0);
      if (this.d >= 131072) {
        this.a = true;
      }
      this.c = true;
    }
  }
}


/* Location:           F:\apktool\apktool\com.google.android.apps.plus\classes-dex2jar.jar
 * Qualified Name:     lsm
 * JD-Core Version:    0.7.0.1
 */